Workbook

Sheet Knowledge Map
A1: Nature Repair Ontology — Biological Repair Logic → Engineering Reasoning | L1: 60-paper mapping snapshot
A2: Expanded from the 60-paper literature map and integrated with the attached reviews, primary studies, thesis, supporting information, and preprints. Core reasoning architecture: DETECT → STABILIZE / CONTAIN → MOBILIZE → RECONSTRUCT → REMODEL / VERIFY.
L3: Strategy | M3: Mapped evidence links
A4: Repair architecture: the sequence the engine should reason through | L4: =A15&" "&B15 -> NR01 Protect / prevent damage | M4: =J15 -> 2
A5: Phase | B5: Core question | C5: Nature logic | D5: Key ontology fields | E5: Representative strategies | L5: =A16&" "&B16 -> NR02 Contain / compartmentalize | M5: =J16 -> 0
A6: 0 PREVENT | B6: Can damage be avoided or reduced before repair is needed? | C6: Protect vulnerable tissue; renew exposed surfaces; deflect cracks. | D6: Damage type • exposure • protective layer • sacrificial zone | E6: NR01 Protect; NR07 Renew/Shed; NR10 Hierarchical crack control | L6: =A17&" "&B17 -> NR03 Rapid plug / seal | M6: =J17 -> 0
A7: 1 DETECT | B7: What changed, where, and how severe is it? | C7: Mechanical/chemical recognition initiates a local response. | D7: Sensor • threshold • location • feedback signal | E7: NR15 Sense→Signal→Repair | L7: =A18&" "&B18 -> NR04 Adhesive rejoin | M7: =J18 -> 10
A8: 2 STABILIZE / CONTAIN | B8: What must happen immediately to stop cascading failure? | C8: Clot, seal, isolate, sacrifice, or arrest propagation before full repair. | D8: Urgency • leak/ingress • propagation risk • containment boundary | E8: NR02 Contain; NR03 Plug/Seal; NR04 Adhesive rejoin; NR09 Sacrificial recovery | L8: =A19&" "&B19 -> NR05 Reservoir release | M8: =J19 -> 3
A9: 3 MOBILIZE | B9: Where do repair resources come from and how do they reach damage? | C9: Release stored material, transport through networks, recruit cells, or use ambient resources. | D9: Resource location • transport • energy • depletion • access | E9: NR05 Reservoir release; NR06 Vascular transport; NR14 Adaptive reconfiguration | L9: =A20&" "&B20 -> NR06 Vascular transport / replenishment | M9: =J20 -> 7
A10: 4 RECONSTRUCT | B10: How is continuity or missing material restored? | C10: Rebond, deposit mineral, regrow tissue, or recycle mobile matter. | D10: Reconstruction mode • scale • interface contact • chemistry | E10: NR08 Dynamic rebond; NR11 Biomineralize/Regrow; NR13 Dissolve→Redistribute→Redeploy | L10: =A21&" "&B21 -> NR07 Layer / renew / shed | M10: =J21 -> 0
A11: 5 REMODEL / VERIFY | B11: Has the relevant function returned, and can the system recover again? | C11: Remodel, restore multiple functions, monitor status, replenish resources. | D11: Function restored • recovery metric • cycles • depth • residual defect | E11: NR12 Living remodeling; NR15 Sense→Signal→Repair; NR16 Staged repair | L11: =A22&" "&B22 -> NR08 Dynamic rebond | M11: =J22 -> 33
L12: =A23&" "&B23 -> NR09 Sacrificial dissipation + recovery | M12: =J23 -> 10
A13: 16 reusable Nature Repair strategies | L13: =A24&" "&B24 -> NR10 Hierarchical crack control | M13: =J24 -> 20
A14: ID | B14: Strategy | C14: Primary phase | D14: Biological primitive | E14: Representative biological models | F14: Abstract engineering rule | G14: Typical trigger | H14: Repeatability | I14: Primary trade-off | J14: 60-paper links* | L14: =A25&" "&B25 -> NR11 Biomineralize / regrow missing material | M14: =J25 -> 6
A15: NR01 | B15: Protect / prevent damage | C15: 0 Prevent | D15: Protective surface | E15: Bark; arthropod exoskeleton; skin | F15: Place a durable or functional outer layer ahead of vulnerable structure so damage is absorbed, repelled, or slowed before it reaches critical material. | G15: Exposure / contact / environment | H15: Continuous if renewed | I15: Added layer can add mass, stiffness, or transport resistance | J15: =COUNTIF(Paper→Ontology!$E$5:$E$64,A15)+COUNTIF(Paper→Ontology!$F$5:$F$64,A15) -> 2 | L15: =A26&" "&B26 -> NR12 Living remodeling / regeneration | M15: =J26 -> 3
A16: NR02 | B16: Contain / compartmentalize | C16: 2 Stabilize | D16: Compartmentalization / boundary formation | E16: Trees (CODIT); immune barriers | F16: When full restoration is costly or risky, isolate the damaged zone with physical/chemical boundaries to prevent propagation. | G16: Damage / infection / ingress | H16: Potentially repeatable in new zones | I16: Sacrifices local function or material | J16: =COUNTIF(Paper→Ontology!$E$5:$E$64,A16)+COUNTIF(Paper→Ontology!$F$5:$F$64,A16) -> 0 | L16: =A27&" "&B27 -> NR13 Dissolve → redistribute → redeploy | M16: =J27 -> 0
A17: NR03 | B17: Rapid plug / seal | C17: 2 Stabilize | D17: Clotting / aggregation | E17: Blood clotting; hemolymph clotting; plant wound exudates | F17: Aggregate or precipitate material rapidly at the breach to stop leakage/ingress before slower reconstruction. | G17: Breach / fluid flow / local chemistry | H17: Usually limited unless resources replenish | I17: Fast sealing may not restore strength | J17: =COUNTIF(Paper→Ontology!$E$5:$E$64,A17)+COUNTIF(Paper→Ontology!$F$5:$F$64,A17) -> 0 | L17: =A28&" "&B28 -> NR14 Adaptive reconfiguration | M17: =J28 -> 9
A18: NR04 | B18: Adhesive rejoin | C18: 2 Stabilize | D18: Wet adhesion / interfacial bonding | E18: Mussel byssus; tissue adhesion | F18: Create high-affinity reversible or covalent interactions at damaged interfaces so separated surfaces reconnect under wet or dynamic conditions. | G18: Contact / water / pH / ions | H18: Multiple if bonds reversible | I18: Strong adhesion can reduce molecular mobility | J18: =COUNTIF(Paper→Ontology!$E$5:$E$64,A18)+COUNTIF(Paper→Ontology!$F$5:$F$64,A18) -> 10 | L18: =A29&" "&B29 -> NR15 Sense → signal → recruit / repair | M18: =J29 -> 11
A19: NR05 | B19: Reservoir release | C19: 3 Mobilize | D19: Vascular cells / capsules | E19: Weeping fig latex cells; secretory cells | F19: Store reactive resources separately and release them only when damage intersects the reservoir. | G19: Crack rupture / chemical trigger | H19: Often single-shot locally | I19: Finite payload; capsule must survive processing yet rupture on demand | J19: =COUNTIF(Paper→Ontology!$E$5:$E$64,A19)+COUNTIF(Paper→Ontology!$F$5:$F$64,A19) -> 3 | L19: =A30&" "&B30 -> NR16 Staged / temporal repair | M19: =J30 -> 6
A20: NR06 | B20: Vascular transport / replenishment | C20: 3 Mobilize | D20: Vascular network | E20: Blood vessels; plant vasculature | F20: Use connected channels to deliver, redistribute, and if possible replenish repair resources over distance and through repeated cycles. | G20: Pressure / capillarity / pumping / damage | H20: Multiple; potentially continuous with reservoir | I20: Network damage, blockage, complexity, volume penalty | J20: =COUNTIF(Paper→Ontology!$E$5:$E$64,A20)+COUNTIF(Paper→Ontology!$F$5:$F$64,A20) -> 7
A21: NR07 | B21: Layer / renew / shed | C21: 0 Prevent + 5 Remodel | D21: Layering + replenishable coating + abscission | E21: Snake skin; tree bark; lotus wax; plant abscission | F21: Continuously grow or replenish protective material from beneath; when damaged material is expendable, isolate then remove/shed it. | G21: Wear / growth / programmed biochemical trigger | H21: Continuous / periodic | I21: Consumes material/energy; discarded layer may be acceptable only in some systems | J21: =COUNTIF(Paper→Ontology!$E$5:$E$64,A21)+COUNTIF(Paper→Ontology!$F$5:$F$64,A21) -> 0
A22: NR08 | B22: Dynamic rebond | C22: 4 Reconstruct | D22: Reversible chemical/physical bonding | E22: Protein networks; ECM-like hydrogels; mussel-inspired networks | F22: Build reversible bonds into the load path so broken interfaces can reorganize and reconnect after damage. | G22: Contact; heat; water; pH; light; ions | H22: Multiple cycles | I22: Strength–mobility trade-off; surfaces often need re-contact | J22: =COUNTIF(Paper→Ontology!$E$5:$E$64,A22)+COUNTIF(Paper→Ontology!$F$5:$F$64,A22) -> 33
A23: NR09 | B23: Sacrificial dissipation + recovery | C23: 2 Stabilize + 4 Reconstruct | D23: Sacrificial bonds | E23: Mussel byssus; bone; nacre; tough tissue | F23: Let selected weaker bonds/domains fail first to dissipate energy while preserving the primary skeleton, then reform the sacrificial network. | G23: Mechanical load then unloading | H23: Multiple | I23: Dissipation may leave residual deformation; recovery kinetics matter | J23: =COUNTIF(Paper→Ontology!$E$5:$E$64,A23)+COUNTIF(Paper→Ontology!$F$5:$F$64,A23) -> 10
A24: NR10 | B24: Hierarchical crack control | C24: 0 Prevent + 2 Stabilize | D24: Hierarchy / crack deflection | E24: Tooth enamel; nacre; bone; fibrous tissue | F24: Arrange hard/soft phases and interfaces across scales to redistribute stress, deflect/blunt cracks, and preserve local mobility needed for repair. | G24: Mechanical damage / stress concentration | H24: Structural feature; not depleted | I24: Complex fabrication; too much reinforcement can suppress healing mobility | J24: =COUNTIF(Paper→Ontology!$E$5:$E$64,A24)+COUNTIF(Paper→Ontology!$F$5:$F$64,A24) -> 20
A25: NR11 | B25: Biomineralize / regrow missing material | C25: 4 Reconstruct | D25: Biomineralization / deposition | E25: Bone; shell; bacteria; fungi; algae | F25: Generate new solid phase in situ using local ions, metabolism, or crystallization so voids are filled rather than merely glued. | G25: Moisture; nutrients; ions; metabolism | H25: Multiple while agents/resources remain viable | I25: Resource access, environmental window, by-products, penetration depth | J25: =COUNTIF(Paper→Ontology!$E$5:$E$64,A25)+COUNTIF(Paper→Ontology!$F$5:$F$64,A25) -> 6
A26: NR12 | B26: Living remodeling / regeneration | C26: 5 Remodel | D26: Cellular growth + matrix turnover | E26: Skin; bone; tendon; regenerative tissue | F26: Continue rebuilding after closure: remove damaged material, replace matrix, reorganize structure, and restore function over longer time scales. | G26: Biological activity / load / signaling | H26: Continuous while living system remains viable | I26: Slow; resource- and control-intensive | J26: =COUNTIF(Paper→Ontology!$E$5:$E$64,A26)+COUNTIF(Paper→Ontology!$F$5:$F$64,A26) -> 3
A27: NR13 | B27: Dissolve → redistribute → redeploy | C27: 3 Mobilize + 4 Reconstruct | D27: Fibrinolysis / phase-transfer recycling | E27: Blood-vessel fibrinolysis analogue; Li–S self-healing electrolyte | F27: Convert obstructive or stranded material into a mobile phase, redistribute it, then reincorporate it into the functional cycle. | G27: Chemical potential / charge-discharge / solubility | H27: Multiple cycles | I27: Must suppress unwanted transport while enabling controlled remobilization | J27: =COUNTIF(Paper→Ontology!$E$5:$E$64,A27)+COUNTIF(Paper→Ontology!$F$5:$F$64,A27) -> 0
A28: NR14 | B28: Adaptive reconfiguration | C28: 3 Mobilize + 4 Reconstruct | D28: Reversible state change / rate-sensitive interactions | E28: Muscle; chameleon skin; bound-water networks; sea-cucumber-like adaptive tissue | F28: Change bond state, stiffness, transport, or architecture according to load rate or environment, then reverse when conditions normalize. | G28: Rate / strain / ions / water / temperature | H28: Multiple | I28: Response window and kinetics must match the disturbance | J28: =COUNTIF(Paper→Ontology!$E$5:$E$64,A28)+COUNTIF(Paper→Ontology!$F$5:$F$64,A28) -> 9
A29: NR15 | B29: Sense → signal → recruit / repair | C29: 1 Detect + 5 Verify | D29: Cellular signaling / mechanosensing | E29: Immune response; dermis; plant recognition; smart hydrogels | F29: Couple damage detection to a localized signal that recruits resources, changes chemistry, or reports repair status; measure functional recovery, not only closure. | G29: Stress; strain; chemistry; electrical / optical change | H29: Multiple if sensing path recovers | I29: Signal can recover differently from mechanics; false positives/threshold design | J29: =COUNTIF(Paper→Ontology!$E$5:$E$64,A29)+COUNTIF(Paper→Ontology!$F$5:$F$64,A29) -> 11
A30: NR16 | B30: Staged / temporal repair | C30: 2→5 sequence | D30: Sequential response / homeostasis | E30: Hemostasis→tissue repair; skin wound healing; plant multistage defense | F30: Assign different functions to different time scales: immediate stabilization first, then reconstruction, then remodeling/verification. | G30: Damage + time + evolving local conditions | H30: Multiple if underlying resources renew | I30: Coordination complexity; early response can obstruct later regeneration | J30: =COUNTIF(Paper→Ontology!$E$5:$E$64,A30)+COUNTIF(Paper→Ontology!$F$5:$F$64,A30) -> 6
A32: Cross-cutting constraints: what the reasoning engine must check before recommending a repair strategy
A33: Dimension | B33: Controlled values / examples | C33: Why it is first-class | D33: Failure if ignored
A34: Damage topology | B34: surface scratch • interface separation • microcrack • deep crack • distributed fatigue • missing volume | C34: Repair access and transport path differ by geometry. | D34: A surface can appear closed while the interior remains damaged.
A35: Function to restore | B35: barrier / watertightness • strength • stiffness • toughness • adhesion • electrical • actuation • biological | C35: 'Healed' must mean recovery of a named function. | D35: Self-sealing can be misreported as structural healing.
A36: Resource location | B36: intrinsic network • local capsule • distributed network • ambient • external • living/metabolic | C36: Determines autonomy and depletion. | D36: A one-shot capsule cannot support unlimited recurrence.
A37: Resource accessibility | B37: open surface • internal crack • vascularly accessible • light-exposed • moisture-exposed | C37: Biological agents and triggers need access. | D37: Algae may work at exposed surfaces but light is unavailable deep inside bulk concrete.
A38: Trigger / activation window | B38: damage • water • pH • heat • light/NIR • electrical • ions • strain rate • metabolism | C38: A mechanism is only useful if real operating conditions activate it. | D38: High-temperature healing chemistry may be impractical in service.
A39: Transport / penetration | B39: diffusion • capillarity • vascular flow • cell growth • ionic migration • none | C39: Controls how far repair reaches into damage. | D39: Crack-mouth closure may overestimate deep healing.
A40: Temporal profile | B40: seconds/minutes • hours • days • weeks • staged | C40: Urgent stabilization and full reconstruction often require different mechanisms. | D40: Slow healing may allow corrosion or crack growth before repair completes.
A41: Repeatability / depletion | B41: single-shot • finite multi-cycle • replenishable • continuous | C41: Sets lifecycle value. | D41: Finite reagents can be exhausted at recurrent damage sites.
A42: Scale match | B42: molecular • interface • microcrack • macrocrack • component | C42: Mechanism must operate at the same scale as failure. | D42: Dynamic rebonding cannot bridge a large gap if faces do not reconnect.
A43: Trade-off budget | B43: strength↔mobility • stiffness↔healing • protection↔transport • speed↔completeness | C43: Nature often distributes conflicting functions across scales, layers, or time. | D43: Optimizing healing alone can weaken the undamaged material.
L44: Evidence status | M44: Interpretation
A45: *Paper counts are taxonomy-level mappings from the existing 60-paper dataset; attached sources add ontology evidence and constraints and are catalogued separately. | L45: Very High / High | M45: Peer-reviewed primary or strong directly supported synthesis
L46: Medium | M46: Review/proceedings or indirect mechanism support
L47: Low–Medium | M47: Preprint or supporting information; provisional
L48: Inference | M48: Ontology transfer rule; not a direct biological observation

Sheet Papers (60)
A1: Paper ID | B1: Cohort | C1: Year | D1: Title | E1: Journal | F1: Biological model | G1: Biological challenge | H1: Mechanism | I1: Abstracted design principle | J1: Primary strategy | K1: Secondary strategy | L1: Healing mode | M1: Trigger | N1: Repeatability | O1: Engineering implementation | P1: Application domain | Q1: Citation signal | R1: Source link (checked at compile) | S1: Notes | T1: Maturity level | U1: Maturity evidence | V1: Scale-up blocker | W1: ◄ Ontology function | X1: ◄ Ontology strategy | Y1: ◄ Operating principle
A2: B01 | B2: Base set | C2: 2026 | D2: Enamel-inspired composite with robust mechanical properties and self-healing capability | E2: Nature Communications | F2: Tooth enamel | G2: Remain stiff/strong while resisting crack propagation and restoring damage | H2: Aligned hydroxyapatite nanowires in a reversible borate-bond polymer network | I2: Combine hard aligned mineral architecture with a mobile, reversible interphase so strength and healing coexist | J2: S7 Hierarchical confinement / crack deflection | K2: S5 Dynamic rebonding | L2: Intrinsic / stimulus-assisted | M2: Heat + water | N2: Repeatable | O2: PVA/boric-acid/HAP nanowire composite | P2: Structural materials; automotive; construction | Q2: Recent 2026 | R2: https://www.nature.com/articles/s41467-026-72309-8 | S2: Validated 2026 paper; reported high healing efficiency and strong mechanical performance. | T2: Lab-scale (assumed) | U2: [VERIFY — inferred from paper type, not confirmed] | V2: [to complete] | W2: Strength | X2: Layering; crack deflection; load distribution | Y2: Multi-scale
A3: B02 | B3: Base set | C3: 2026 | D3: Bound water as a kinetic crosslinker for bio-inspired impact-stiffening polymers | E3: Nature Communications | F3: Water-mediated mechanics in biological materials | G3: Stay soft in normal use but stiffen and dissipate energy under rapid loading, then recover | H3: Bound water acts as a rate-sensitive kinetic crosslinker controlling intermolecular coupling | I3: Use a normally passive component as a load-rate-dependent temporary crosslinker | J3: S10 Adaptive remodeling / living repair | K3: S5 Dynamic rebonding | L3: Intrinsic / adaptive | M3: Impact / loading rate | N3: Repeatable | O3: Water-mediated dynamic polymer network | P3: Impact protection; adaptive structures | Q3: Recent 2026 | R3: https://www.nature.com/articles/s41467-026-75737-8 | S3: Mechanism is especially relevant to adaptive repair and impact response. | T3: Lab-scale (assumed) | U3: [VERIFY — inferred from paper type, not confirmed] | V3: [to complete] | W3: Adaptation | X3: Variation; behavioural flexibility | Y3: Self-repair
A4: B03 | B4: Base set | C4: 2026 | D4: Bioinspired Time-Gradient Self-Healing Polyurethane/Epoxy Covalent Dynamic Networks Enhanced by GO/ZIF-8@Curcumin for Marine Protection | E4: Small | F4: Skin wound healing | G4: Stabilize damage quickly, then rebuild more fully over time | H4: Fast extrinsic response combined with slower intrinsic dynamic-covalent reconstruction | I4: Sequence repair mechanisms rather than asking one mechanism to satisfy all time scales | J4: S9 Staged / temporal repair | K4: S5 Dynamic rebonding | L4: Hybrid intrinsic + extrinsic | M4: Ambient / time-dependent chemistry | N4: Repeatable | O4: PU/epoxy dynamic network + functional nanocontainers | P4: Marine anticorrosion coatings | Q4: Recent 2026 | R4: https://onlinelibrary.wiley.com/doi/10.1002/smll.74179 | S4: Strong exemplar of temporal sequencing. | T4: Lab-scale (assumed) | U4: [VERIFY — inferred from paper type, not confirmed] | V4: [to complete] | W4: Renewal | X4: Cyclicity; staged sequence | Y4: Spirality
A5: B04 | B5: Base set | C5: 2026 | D5: Bioinspired Self-Healing Polyurethane-Based Ionogel for Dual-Modal Strain Sensing and Solvent-Triggered Alerting | E5: Advanced Functional Materials | F5: Plant cell wall ion migration | G5: Maintain integrity while sensing deformation and environmental change | H5: Swelling-enhanced ion migration coupled to dynamic polyurethane bonding | I5: Couple repair with reversible ion transport so the same material can heal and sense | J5: S8 Sense → signal → repair | K5: S5 Dynamic rebonding | L5: Intrinsic / multifunctional | M5: Strain + solvent/environment | N5: Repeatable | O5: Polyurethane ionogel | P5: Wearables; strain sensing; chemical alerts | Q5: Recent 2026 | R5: https://advanced.onlinelibrary.wiley.com/doi/10.1002/adfm.76566 | S5: Explicitly plant-inspired. | T5: Lab-scale (assumed) | U5: [VERIFY — inferred from paper type, not confirmed] | V5: [to complete] | W5: Communication & feedback | X5: Closed feedback loop; damage signalling | Y5: Locality
A6: B05 | B6: Base set | C6: 2026 | D6: Skin-Inspired Design of Self-Healing Coatings Integrating Interface-Liquid Repellency and Corrosion Resistance | E6: Advanced Science | F6: Multilayer human skin | G6: Combine barrier protection, interface control, and healing without one function degrading another | H6: Layered/graded architecture with self-healing and liquid-repellent interfaces | I6: Spatially separate conflicting functions across layers and reconnect them after damage | J6: S1 Rapid seal / adhesion | K6: S9 Staged / temporal repair | L6: Intrinsic / layered | M6: Aqueous exposure + dynamic bonding | N6: Repeatable | O6: Multilayer protective coating | P6: Corrosion protection | Q6: Recent 2026 | R6: https://advanced.onlinelibrary.wiley.com/doi/10.1002/advs.202521067 | S6: Validated 2026 paper. | T6: Lab-scale (assumed) | U6: [VERIFY — inferred from paper type, not confirmed] | V6: [to complete] | W6: Protective envelope | X6: Selectively permeable boundary; surface sealing | Y6: Locality
A7: B06 | B7: Base set | C7: 2026 | D7: Dermis-Inspired Multimodal and Reversible Damaging-Healing Monitoring Coating via Dynamic Bonding Synchronous Activation Strategy | E7: Advanced Functional Materials | F7: Dermis / tissue damage signaling | G7: Detect accumulating damage and track healing progress while preserving protection | H7: Dynamic-bond reconstruction is coupled with a reversible optical signaling pathway | I7: Make damage and healing state observable in real time, not just mechanically repairable | J7: S8 Sense → signal → repair | K7: S5 Dynamic rebonding | L7: Intrinsic / self-reporting | M7: Mechanical damage + bond reconstruction | N7: Repeatable | O7: Smart protective coating | P7: Marine and structural coatings | Q7: Recent 2026 | R7: https://advanced.onlinelibrary.wiley.com/doi/10.1002/adfm.75334 | S7: Validated 2026 paper. | T7: Lab-scale (assumed) | U7: [VERIFY — inferred from paper type, not confirmed] | V7: [to complete] | W7: Communication & feedback | X7: Closed feedback loop; damage signalling | Y7: Locality
A8: B07 | B8: Base set | C8: 2026 | D8: Bioinspired super-tough polyurethane elastomers with block modules using sacrificial bonds | E8: RSC Advances | F8: Tough biological tissues / mussel byssus | G8: Absorb large deformation without catastrophic failure and recover reversible interactions | H8: Hierarchical sacrificial H-bonds and metal coordination in modular polyurethane | I8: Use multiple bond strengths so weaker bonds dissipate energy while stronger structure remains | J8: S6 Sacrificial-bond recovery | K8: S5 Dynamic rebonding | L8: Intrinsic | M8: Mechanical unloading / reversible bonding | N8: Repeatable | O8: Polyurethane elastomer | P8: E-skin; flexible devices; robotics | Q8: Recent 2026 | R8: https://pubs.rsc.org/en/content/articlelanding/2026/ra/d5ra08303f | S8: Explicitly bioinspired. | T8: Lab-scale (assumed) | U8: [VERIFY — inferred from paper type, not confirmed] | V8: [to complete] | W8: Strength | X8: Energy absorption; sacrificial bonds | Y8: Gradient
A9: B08 | B9: Base set | C9: 2026 | D9: Bioinspired Design of Strong, Tough, and Room-Temperature Healable Silicone Elastomers by Dynamic Nanoconfinement | E9: Macromolecules | F9: Hierarchical protein materials / spider-silk-like organization | G9: Combine high strength with chain mobility sufficient for room-temperature repair | H9: Dynamic nanoconfinement localizes strong interactions while leaving mobile healing domains | I9: Confine strong bonds spatially rather than making the whole network rigid | J9: S7 Hierarchical confinement / crack deflection | K9: S5 Dynamic rebonding | L9: Intrinsic | M9: Room temperature contact | N9: Repeatable | O9: Silicone elastomer | P9: Wearables; sensors; recyclable circuits | Q9: Recent 2026 | R9: https://pubs.acs.org/doi/10.1021/acs.macromol.6c00733 | S9: Validated 2026 paper. | T9: Lab-scale (assumed) | U9: [VERIFY — inferred from paper type, not confirmed] | V9: [to complete] | W9: Strength | X9: Layering; crack deflection; load distribution | Y9: Multi-scale
A10: B09 | B10: Base set | C10: 2026 | D10: Bio-Inspired Carbon Fiber/Epoxy Composites With Interfacial Self-Healing Ability Triggered by Electricity | E10: Polymer Composites | F10: Localized biological repair at damage-prone interfaces | G10: Restore damage preferentially where debonding occurs | H10: Electrically triggered interfacial healing chemistry concentrated at fiber/matrix interfaces | I10: Place repair capacity at known failure planes rather than distributing it uniformly | J10: S5 Dynamic rebonding | K10: S7 Hierarchical confinement / crack deflection | L10: Stimulus-assisted | M10: Electrical | N10: Repeated cycles | O10: Carbon-fiber/epoxy interface | P10: Aerospace; automotive composites | Q10: Recent 2026 | R10: https://4spepublications.onlinelibrary.wiley.com/doi/10.1002/pc.70926 | S10: Interface-localized repair exemplar. | T10: Lab-scale (assumed) | U10: [VERIFY — inferred from paper type, not confirmed] | V10: [to complete] | W10: Renewal | X10: Sacrificial bonds; re-bonding | Y10: Self-repair
A11: B10 | B11: Base set | C11: 2026 | D11: Bioinspired “self-healing vaccine” for cementitious materials: Physicochemical synergistic healing mechanisms among multiple cracks | E11: Cement and Concrete Research | F11: Vaccination / externally enabled biological response | G11: Enable existing infrastructure to respond repeatedly to future cracks | H11: External repair treatment supplies reactive resources that migrate/react in damaged cementitious zones | I11: Retrofit a repair capability into an existing system rather than requiring healing to be designed in from manufacture | J11: S4 Biomineralize / regrow | K11: S3 Vascular transport | L11: Extrinsic / externally supplied | M11: Moisture + treatment chemistry | N11: Potentially repeated | O11: Cementitious repair system | P11: Existing concrete infrastructure | Q11: Recent 2026 | R11: https://www.sciencedirect.com/science/article/abs/pii/S0008884626001304 | S11: Useful retrofit principle. | T11: Lab-scale (assumed) | U11: [VERIFY — inferred from paper type, not confirmed] | V11: [to complete] | W11: Renewal | X11: Regrowth; material cycling | Y11: Self-creation
A12: B11 | B12: Base set | C12: 2026 | D12: A strong, healable, recyclable bio-based adhesive via a bone-inspired triple network | E12: Journal of Materials Chemistry A | F12: Bone | G12: Combine stiffness, toughness, repair, and recyclability in one structural adhesive | H12: Triple-network hierarchy with reversible energy-dissipating interactions | I12: Assign different roles to nested networks: load bearing, dissipation, and repair | J12: S7 Hierarchical confinement / crack deflection | K12: S6 Sacrificial-bond recovery | L12: Intrinsic / thermally assisted | M12: Dynamic interactions | N12: Repeatable | O12: Bio-based structural adhesive | P12: Structural bonding | Q12: Recent 2026 | R12: https://pubs.rsc.org/en/content/articlelanding/2026/ta/d6ta01962e | S12: Bone-inspired hierarchy. | T12: Lab-scale (assumed) | U12: [VERIFY — inferred from paper type, not confirmed] | V12: [to complete] | W12: Strength | X12: Layering; crack deflection; load distribution | Y12: Multi-scale
... A61: A40 | B61: Added mechanism anchor | C61: 2017 | D61: Tough adhesives for diverse wet surfaces | E61: Science | F61: Biological wet adhesion / tough tissue interfaces | G61: Maintain strong adhesion to wet, moving, deformable tissues | H61: A dissipative matrix is combined with strong interfacial bonding to create high interfacial toughness | I61: Pair adhesion chemistry with a bulk energy-dissipation layer; interface strength alone is not enough | J61: S1 Rapid seal / adhesion | K61: S6 Sacrificial-bond recovery | L61: Interfacial / tough adhesive | M61: Contact + wet bonding | N61: Reusable concept; formulation dependent | O61: Tough hydrogel adhesive | P61: Tissue sealing; wet structural adhesion | Q61: >1,700 citations surfaced | R61: https://www.science.org/doi/10.1126/science.aah6362 | S61: Mechanism anchor for durable sealing and repair interfaces. | T61: N/A — biological mechanism | U61: Nature, not an engineered system | V61: — | W61: Protective envelope | X61: Selectively permeable boundary; surface sealing | Y61: Locality

Sheet Engine Schema
A1: Nature Repair Ontology — AI / knowledge-graph schema
A2: Recommended data model for converting biological evidence and engineering papers into reasoning-ready records. The engine should retrieve mechanisms by challenge/constraint, not by organism name alone.
A4: Field | B4: Entity / layer | C4: Question the engine answers | D4: Controlled vocabulary / data type | E4: Example | F4: Reasoning role | G4: Required? | H4: Validation rule / caveat
A5: Record_ID | B5: All | C5: What unique assertion/model/paper/strategy is this? | D5: Unique string | E5: BIO-M19 / STR-NR11 / PAP-B01 | F5: Graph identity | G5: Yes | H5: Never reuse IDs across entity types.
A6: Entity_Type | B6: All | C6: What kind of thing is this record? | D6: BiologicalModel / Primitive / Strategy / Paper / Relation / Metric / ChallengeRule | E6: Strategy | F6: Routing | G6: Yes | H6: Controls which fields are applicable.
A7: Biological_Model_ID | B7: Biological evidence | C7: Which organism/tissue/system demonstrates the mechanism? | D7: M01–M30 + expandable | E7: M19 CODIT | F7: Evidence anchor | G7: When biological | H7: One model can map to multiple primitives/strategies.
A8: Biological_Domain | B8: Biological evidence | C8: What type of living system is it? | D8: Animal / plant / microorganism / tissue / cellular / ecological | E8: Woody plant | F8: Transfer context | G8: Recommended | H8: Do not infer taxonomy beyond source support.
A9: Damage_or_Challenge | B9: Problem | C9: What failure must be prevented or repaired? | D9: Functional sentence + damage tags | E9: Stop crack-mediated fluid ingress | F9: Problem abstraction | G9: Yes | H9: State damage, not solution.
A10: Damage_Topology | B10: Problem | C10: What is the geometry/location of damage? | D10: Surface / interface / microcrack / deep crack / distributed / missing volume / deposit | E10: Deep crack | F10: Feasibility filter | G10: Yes | H10: Needed for penetration/access reasoning.
A11: Damage_Severity | B11: Problem | C11: How large/severe is the defect? | D11: Numeric + units + class | E11: 0.4 mm crack | F11: Scale matching | G11: If known | H11: Store original measured value.
A12: Repair_Phase | B12: Ontology | C12: At which step does the mechanism act? | D12: 0 Prevent / 1 Detect / 2 Stabilize / 3 Mobilize / 4 Reconstruct / 5 Remodel-Verify | E12: 3 Mobilize | F12: Sequence planning | G12: Yes | H12: Multi-phase values allowed.
A13: Primitive_IDs | B13: Biological mechanism | C13: What minimal natural actions are present? | D13: P01–P16 array | E13: P06,P11 | F13: Mechanism decomposition | G13: Yes | H13: Prefer evidence-backed primitive assignment.
A14: Strategy_IDs | B14: Engineering abstraction | C14: Which reusable repair strategy/strategies apply? | D14: NR01–NR16 array | E14: NR06,NR11 | F14: Strategy retrieval | G14: Yes | H14: Primary + complementary strategy order matters.
A15: Mechanism | B15: Causal layer | C15: How does the natural/engineered system actually work? | D15: Evidence-backed prose / structured steps | E15: Damage releases latex; capillarity carries it into wound | F15: Causal reasoning | G15: Yes | H15: Avoid metaphor-only descriptions.
... A51: Transfer_Rule | B51: Reasoning output | C51: Under what conditions may this mechanism transfer to another domain? | D51: IF–THEN rule | E51: IF damage recurs at unknown internal locations AND fluid channels are feasible THEN prioritize NR06 | F51: Concept generation | G51: Yes for strategy records | H51: Must include constraints, not only benefits.
A54: Core relation vocabulary for a future knowledge graph
A55: Relation | B55: Meaning | C55: Example
A56: USES_PRIMITIVE | B56: Biological model or strategy employs primitive | C56: M19 USES_PRIMITIVE P09
A57: INSPIRES | B57: Biological model provides causal inspiration for strategy | C57: M03 INSPIRES NR13
A58: TRIGGERED_BY | B58: Response activates under condition | C58: NR11 TRIGGERED_BY moisture/nutrients
A59: REQUIRES | B59: Mechanism is infeasible without condition/resource | C59: NR08 REQUIRES molecular mobility
A60: LIMITED_BY | B60: Known failure boundary | C60: NR05 LIMITED_BY finite payload
A61: PRECEDES | B61: Temporal order | C61: NR03 PRECEDES NR12
A62: COMPLEMENTS | B62: Strategies improve each other | C62: NR10 COMPLEMENTS NR08
A63: CONFLICTS_WITH | B63: One response can impede another | C63: NR03 CAN CONFLICT WITH deep transport
A64: RESTORES_FUNCTION | B64: Names recovered capability | C64: NR03 RESTORES_FUNCTION barrier
A65: MEASURE_WITH | B65: Links strategy to metric ontology | C65: NR11 MEASURE_WITH E01,E02,E03,E04
A66: NOT_EQUIVALENT_TO | B66: Prevents category errors | C66: Self-sealing NOT_EQUIVALENT_TO strength recovery

Sheet Legacy Map (10)
A1: Nature Self-Healing Knowledge Map
A2: 60 validated academic papers mapped by reusable biological repair strategy • 20-paper base set + 40 additional high-impact / foundational papers
A4: Strategy | B4: Biological analogs | C4: What nature solves | D4: Abstracted design principle | E4: Typical engineering translation | F4: Typical triggers | G4: Paper count | I4: Strategy profile | J4: Papers
A5: S1 Rapid seal / adhesion | B5: Mussels, skin, clotting/tissue closure | C5: Create fast wet adhesion or sealing at the damaged interface to stop further ingress, leakage, or separation. | D5: Dynamic catechol/metal, covalent tissue bonding, reversible adhesive interfaces | E5: Adhesive hydrogel/coating/interface that closes or seals a damaged boundary before secondary damage propagates. | F5: Water, pH, contact, local chemistry | G5: 7 | I5: Rapid seal / adhesion | J5: 7
A6: S2 Reservoir release | B6: Cells/organisms storing and releasing repair resources | C6: Store healing agents locally; damage ruptures a reservoir and releases material exactly where needed. | D6: Microcapsules, hollow fibers, sacrificial reservoirs | E6: Embed microcapsules/reservoirs that rupture on crack formation and release healing chemistry locally. | F6: Crack rupture / mechanical damage | G6: 1 | I6: Reservoir release | J6: 1
A7: S3 Vascular transport | B7: Blood vessels, plant vasculature | C7: Use connected channels to transport and replenish healing agents so repair can occur repeatedly and over larger volumes. | D7: Microvascular networks, multi-channel delivery, replenishable vascules | E7: Build refillable microchannel networks that deliver repair agents repeatedly to damaged zones. | F7: Damage-induced flow, pressure, pumping | G7: 6 | I7: Vascular transport | J7: 6
A8: S4 Biomineralize / regrow | B8: Bone, shell formation, microbial biomineralization | C8: Generate new solid material in situ to fill defects and restore barrier or load-bearing function. | D8: Bacteria-induced CaCO3, mineral precipitation, regenerative matrices | E8: Generate new mineral/solid phase in situ through microbes, ions, or precipitation rather than merely gluing cracks. | F8: Moisture, nutrients, microbial metabolism | G8: 6 | I8: Biomineralize / regrow | J8: 6
A9: S5 Dynamic rebonding | B9: Protein networks, mussel catechol chemistry, squid ring teeth | C9: Use reversible bonds that break under damage and re-form afterward, enabling repeatable repair. | D9: H-bonds, metal-ligand bonds, boronate esters, imines, dynamic covalent networks | E9: Use reversible covalent, hydrogen-bond, ionic, metal–ligand, or supramolecular bonds that re-form after damage. | F9: Ambient contact, heat, pH, water, ions | G9: 10 | I9: Dynamic rebonding | J9: 10
A10: S6 Sacrificial-bond recovery | B10: Mussel byssus, bone, nacre, tough biological tissues | C10: Allow selected weaker bonds/domains to fail first, dissipate energy, then reconnect while the main structure survives. | D10: Hierarchical weak/strong bonds, metal-catechol, multiple H-bond domains | E10: Place weaker reversible bonds ahead of the load-bearing network so they dissipate energy, then recover. | F10: Mechanical loading followed by rebonding | G10: 4 | I10: Sacrificial-bond recovery | J10: 4
A11: S7 Hierarchical confinement / crack deflection | B11: Nacre, enamel, bone, vascular smooth muscle, squid ring teeth | C11: Control damage path across scales; use hard-soft hierarchy, nanoconfinement, and interfaces to blunt/deflect cracks while retaining mobility for healing. | D11: Brick-and-mortar architectures, aligned platelets/nanowires, confined dynamic phases, core-shell inclusions | E11: Use hard–soft hierarchy, aligned reinforcement, interfaces or nanoconfinement to arrest cracks while preserving local mobility. | F11: Heat, local mobility, deformation | G11: 10 | I11: Hierarchy / crack deflection | J11: 10
A12: S8 Sense → signal → repair | B12: Skin, mechanoreceptors, plant ion transport | C12: Couple damage detection with a visible/electrical/mechanical signal and activate or monitor repair. | D12: Mechanochromism, ion transport, conductive pathways, damage-responsive chemistry | E12: Couple damage detection to optical/electrical/mechanical signaling and, ideally, activation of the repair pathway. | F12: Stress, strain, solvent, pressure, electrical/NIR | G12: 8 | I12: Sense → signal → repair | J12: 8
A13: S9 Staged / temporal repair | B13: Skin wound healing, embryonic wound closure | C13: Sequence different repair functions over time: fast stabilization first, slower structural restoration later. | D13: Fast extrinsic + slow intrinsic repair; time-gradient chemistry | E13: Assign different repair functions to different time scales: rapid stabilization first, slower reconstruction afterward. | F13: Time, local chemistry, temperature | G13: 2 | I13: Staged / temporal repair | J13: 2
A14: S10 Adaptive remodeling / living repair | B14: Sea cucumber dermis, living tissues, regenerative systems | C14: Adapt stiffness/function to the environment, then remodel or regenerate rather than merely close a crack. | D14: Stimuli-responsive networks, living materials, regenerative hydrogels | E14: Allow stiffness, architecture or biological activity to adapt over time and rebuild function rather than simply close a defect. | F14: Water, ionic environment, biological activity, external stimuli | G14: 6 | I14: Adaptive / living repair | J14: 6
A17: Cross-cutting dimensions for a Nature Intelligence self-healing reasoning engine
A18: Dimension | B18: Possible values | C18: Why it matters | D18: Example biological logic
A19: Trigger | B19: Damage • water • pH • heat • light/NIR • electrical • enzymatic • microbial • spontaneous | C19: Defines what initiates repair and whether external energy is required. | D19: Wounds activate coagulation; plants respond to moisture/ionic changes.
A20: Resource location | B20: Local • embedded capsule • distributed network • external • living | C20: Determines how repair resources are stored and replenished. | D20: Cells store factors locally; vascular systems transport resources.
A21: Repair scale | B21: Molecular • interface • microcrack • macrocrack • tissue/structure | C21: Prevents choosing a mechanism that operates at the wrong damage scale. | D21: Proteins rebind molecularly while bone remodels across larger volumes.
A22: Repeatability | B22: Single-shot • multiple-cycle • continuous | C22: Separates one-time emergency repair from durable regenerative capability. | D22: Capsules are often one-shot; vascular/living systems can replenish.
A23: Autonomy | B23: Autonomous • stimulus-assisted • externally replenished | C23: Controls system complexity, energy demand and maintenance burden. | D23: Skin heals autonomously; some biological processes depend on external nutrients.
A24: Temporal profile | B24: Immediate • staged • delayed • slow remodeling | C24: Allows repair architecture to optimize speed versus completeness. | D24: Hemostasis is rapid; tissue remodeling is slower.
A25: Feedback | B25: None • visual • electrical • mechanical • chemical | C25: Enables the material/system to report damage and repair status. | D25: Inflammatory signaling and mechanosensing provide feedback.
A26: Function restored | B26: Mechanical • barrier • electrical • adhesion • actuation • biological | C26: Defines what 'healed' actually means in system performance terms. | D26: Different tissues prioritize barrier, load bearing, signaling or motion.

Sheet Paper→Ontology
A1: Mapping of the existing 60-paper evidence base into the Nature Repair Ontology
A2: This is a taxonomy mapping layer: it preserves the original paper metadata while assigning ontology strategy IDs. It does not replace paper-level mechanism extraction.
A4: Paper ID | B4: Year | C4: Title | D4: Biological model | E4: Ontology primary | F4: Ontology secondary | G4: Repair phase | H4: Trigger | I4: Repeatability | J4: Validated source
A5: B01 | B5: 2026 | C5: Enamel-inspired composite with robust mechanical properties and self-healing capability | D5: Tooth enamel | E5: NR10 | F5: NR08 | G5: 0 Prevent / 2 Stabilize | H5: Heat + water | I5: Repeatable | J5: https://www.nature.com/articles/s41467-026-72309-8
A6: B02 | B6: 2026 | C6: Bound water as a kinetic crosslinker for bio-inspired impact-stiffening polymers | D6: Water-mediated mechanics in biological materials | E6: NR14 | F6: NR08 | G6: 3 Mobilize / 4 Reconstruct | H6: Impact / loading rate | I6: Repeatable | J6: https://www.nature.com/articles/s41467-026-75737-8
A7: B03 | B7: 2026 | C7: Bioinspired Time-Gradient Self-Healing Polyurethane/Epoxy Covalent Dynamic Networks Enhanced by GO/ZIF-8@Curcumin for Marine Protection | D7: Skin wound healing | E7: NR16 | F7: NR08 | G7: 2–5 staged | H7: Ambient / time-dependent chemistry | I7: Repeatable | J7: https://onlinelibrary.wiley.com/doi/10.1002/smll.74179
A8: B04 | B8: 2026 | C8: Bioinspired Self-Healing Polyurethane-Based Ionogel for Dual-Modal Strain Sensing and Solvent-Triggered Alerting | D8: Plant cell wall ion migration | E8: NR15 | F8: NR08 | G8: 1 Detect / 5 Verify | H8: Strain + solvent/environment | I8: Repeatable | J8: https://advanced.onlinelibrary.wiley.com/doi/10.1002/adfm.76566
A9: B05 | B9: 2026 | C9: Skin-Inspired Design of Self-Healing Coatings Integrating Interface-Liquid Repellency and Corrosion Resistance | D9: Multilayer human skin | E9: NR01 | F9: NR16 | G9: 0 Prevent | H9: Aqueous exposure + dynamic bonding | I9: Repeatable | J9: https://advanced.onlinelibrary.wiley.com/doi/10.1002/advs.202521067
A10: B06 | B10: 2026 | C10: Dermis-Inspired Multimodal and Reversible Damaging-Healing Monitoring Coating via Dynamic Bonding Synchronous Activation Strategy | D10: Dermis / tissue damage signaling | E10: NR15 | F10: NR08 | G10: 1 Detect / 5 Verify | H10: Mechanical damage + bond reconstruction | I10: Repeatable | J10: https://advanced.onlinelibrary.wiley.com/doi/10.1002/adfm.75334
A11: B07 | B11: 2026 | C11: Bioinspired super-tough polyurethane elastomers with block modules using sacrificial bonds | D11: Tough biological tissues / mussel byssus | E11: NR09 | F11: NR08 | G11: 2 Stabilize / 4 Reconstruct | H11: Mechanical unloading / reversible bonding | I11: Repeatable | J11: https://pubs.rsc.org/en/content/articlelanding/2026/ra/d5ra08303f
A12: B08 | B12: 2026 | C12: Bioinspired Design of Strong, Tough, and Room-Temperature Healable Silicone Elastomers by Dynamic Nanoconfinement | D12: Hierarchical protein materials / spider-silk-like organization | E12: NR10 | F12: NR08 | G12: 0 Prevent / 2 Stabilize | H12: Room temperature contact | I12: Repeatable | J12: https://pubs.acs.org/doi/10.1021/acs.macromol.6c00733
A13: B09 | B13: 2026 | C13: Bio-Inspired Carbon Fiber/Epoxy Composites With Interfacial Self-Healing Ability Triggered by Electricity | D13: Localized biological repair at damage-prone interfaces | E13: NR08 | F13: NR10 | G13: 4 Reconstruct | H13: Electrical | I13: Repeated cycles | J13: https://4spepublications.onlinelibrary.wiley.com/doi/10.1002/pc.70926
A14: B10 | B14: 2026 | C14: Bioinspired “self-healing vaccine” for cementitious materials: Physicochemical synergistic healing mechanisms among multiple cracks | D14: Vaccination / externally enabled biological response | E14: NR11 | F14: NR06 | G14: 4 Reconstruct | H14: Moisture + treatment chemistry | I14: Potentially repeated | J14: https://www.sciencedirect.com/science/article/abs/pii/S0008884626001304
A15: B11 | B15: 2026 | C15: A strong, healable, recyclable bio-based adhesive via a bone-inspired triple network | D15: Bone | E15: NR10 | F15: NR09 | G15: 0 Prevent / 2 Stabilize | H15: Dynamic interactions | I15: Repeatable | J15: https://pubs.rsc.org/en/content/articlelanding/2026/ta/d6ta01962e
... A64: A40 | B64: 2017 | C64: Tough adhesives for diverse wet surfaces | D64: Biological wet adhesion / tough tissue interfaces | E64: NR04 | F64: NR09 | G64: 2 Stabilize / 4 Reconstruct | H64: Contact + wet bonding | I64: Reusable concept; formulation dependent | J64: https://www.science.org/doi/10.1126/science.aah6362

Sheet Repair Strategies
A1: Nature Repair Ontology — Strategy Definitions and Transfer Rules
A2: Each strategy is a reusable engineering-neutral repair pattern. Biological models are evidence anchors; constraints and failure modes are first-class so the engine can reject unsuitable analogies.
A4: Strategy ID | B4: Strategy | C4: Repair phase(s) | D4: Canonical / extended primitive | E4: Representative biological model | F4: Biological challenge | G4: Natural sequence | H4: Trigger / sensor | I4: Immediate response | J4: Resource / repair material | K4: Resource location | L4: Transport / mobilization | M4: Reconstruction mode | N4: Spatial scale | O4: Temporal profile | P4: Repeatability | Q4: Function(s) restored | R4: Engineering-neutral design rule | S4: Suitable engineering conditions | T4: Main trade-off | U4: Common failure mode | V4: Best complementary strategies | W4: Evidence anchors | X4: Confidence
A5: NR01 | B5: Protect / prevent damage | C5: 0 Prevent | D5: Canonical: protective surface | E5: Tree bark; arthropod exoskeleton; skin; functional plant surfaces | F5: Keep routine environmental or mechanical damage away from vulnerable tissue. | G5: Build tough/functional outer layer → absorb/repel exposure → renew from beneath if needed. | H5: Exposure / contact; often passive | I5: Damage is prevented or shifted to expendable layer | J5: Protective material / surface chemistry | K5: Surface / outer layer | L5: None or replenishment from below | M5: Barrier formation; repellency; sacrificial absorption | N5: Surface → component | O5: Continuous | P5: Continuous if renewed | Q5: Barrier integrity; environmental protection | R5: Put a robust, task-specific layer ahead of vulnerable functions; design that layer to be renewable or sacrificial when possible. | S5: High exposure frequency; surface-dominated failure; contamination/corrosion/fouling risk | T5: Added thickness/mass can impede transport or flexibility | U5: Barrier cracks without renewal; hidden sub-surface damage | V5: NR07, NR10, NR15 | W5: Cremaldi & Bhushan 2018; Youngblood & Sottos 2008 | X5: High
A6: NR02 | B6: Contain / compartmentalize | C6: 2 Stabilize | D6: Extended: boundary formation / damage containment | E6: Trees — compartmentalization of decay (CODIT); immune barriers | F6: Prevent a local defect, infection, or degradation zone from spreading through the whole system. | G6: Detect local damage → form physical + chemical walls → sacrifice/isolate damaged region → continue operation elsewhere. | H6: Local damage / disease chemistry | I6: Propagation pathway is cut | J6: Boundary-forming material / chemistry | K6: At perimeter of damaged zone | L6: Local secretion / growth | M6: Isolation rather than restoration | N6: Local zone → component | O6: Fast boundary formation then persistent | P6: Repeatable in new zones | Q6: System-level continuity / integrity | R6: If full repair is expensive or risky, isolate the failing zone and preserve the rest of the system. | S6: Distributed systems; non-critical local loss acceptable; propagation risk high | T6: Local capacity is sacrificed | U6: Boundary is incomplete; damage bypasses compartment | V6: NR01, NR03, NR16 | W6: Cremaldi & Bhushan 2018 — CODIT | X6: High
A7: NR03 | B7: Rapid plug / seal | C7: 2 Stabilize | D7: Canonical: clotting / aggregation | E7: Blood clotting; invertebrate hemolymph clotting; plant wound secretions | F7: Stop fast loss of fluid or ingress of harmful agents immediately after breach. | G7: Breach → local aggregation/precipitation → plug forms → flow/ingress drops → slower repair follows. | H7: Breach / flow / exposed chemistry | I7: Wound is sealed rapidly | J7: Platelets/proteins/exudate or precipitating material | K7: Circulating or locally stored | L7: Flow + aggregation / capillarity | M7: Plug / precipitate / temporary barrier | N7: Interface / crack | O7: Seconds–minutes biologically; application-dependent | P7: Finite unless replenished | Q7: Barrier / watertightness | R7: Prioritize a fast sealing mechanism that stabilizes the defect even if it does not yet restore load-bearing performance. | S7: Leakage, ingress, corrosion exposure, puncture-like damage | T7: Fast closure can obstruct later reconstruction or provide little mechanical strength | U7: Surface closure mistaken for full-depth healing | V7: NR06, NR11, NR16 | W7: Cremaldi & Bhushan 2018; concrete sealing literature | X7: High
A8: NR04 | B8: Adhesive rejoin | C8: 2 Stabilize + 4 Reconstruct | D8: Extended: wet adhesion / interfacial rebonding | E8: Mussel byssus / adhesive plaque; tissue interfaces | F8: Reconnect separated interfaces under wet, dynamic, or contaminated conditions. | G8: Bring faces into contact → form high-affinity interfacial bonds → dissipate load → reversible bonds reform after disturbance. | H8: Contact; pH; water; ions | I8: Interface reconnects | J8: Catechol-like groups / dynamic bonds | K8: At damaged interface | L8: Diffusion / molecular contact | M8: Adhesive bonding | N8: Molecular → interface | O8: Minutes–hours | P8: Multiple if dynamic | Q8: Adhesion; barrier; sometimes mechanics | R8: Design the damaged interface itself as an active repair zone using reversible, water-compatible, high-affinity interactions. | S8: Delamination, wet adhesion, coatings, tissue interfaces | T8: High bond density can reduce chain mobility | U8: Faces do not re-contact; fouling blocks bonding | V8: NR08, NR09, NR15 | W8: Mussel-inspired papers in 60-paper set | X8: High
A9: NR05 | B9: Reservoir release | C9: 3 Mobilize | D9: Canonical: vascular cells / capsules | E9: Weeping fig latex cells; secretory cells; biological vesicle-like storage | F9: Keep reactive repair resources stable until damage occurs, then release exactly at the wound. | G9: Store agent → damage ruptures container / changes chemistry → agent is released → flows into defect → reacts/solidifies. | H9: Crack rupture; pH; chloride; heat; moisture; electromagnetic trigger | I9: Localized agent release | J9: Healing monomer/resin/mineral precursor/cells | K9: Distributed capsules / granules | L9: Capillarity / local flow | M9: Polymerization / precipitation / swelling | N9: Microcrack → local macrocrack | O9: Fast to hours/days | P9: Usually single-shot at a location | Q9: Barrier + mechanics depending agent | R9: Separate reactive chemistry from the host until a damage-specific trigger releases it. | S9: Sparse unpredictable cracks; manufacturing can tolerate inclusions | T9: Finite payload; capsules change host mechanics | U9: Premature rupture; no capsule intersects crack; payload exhausted | V9: NR03, NR11, NR16 | W9: White et al. 2001 lineage; van der Bergh thesis capsule classification | X9: High
A10: NR06 | B10: Vascular transport / replenishment | C10: 3 Mobilize | D10: Canonical: vascular networks | E10: Blood vessels; plant vasculature; refillable biological transport | F10: Deliver cells, nutrients, enzymes, or repair chemistry over distance and repeatedly. | G10: Damage creates demand → connected network supplies agent → flow reaches defect → repair occurs → reservoir can refill network. | H10: Damage-induced pressure/capillarity or active pumping | I10: Repair resources reach wound | J10: Fluid healing agent / nutrients / cells | K10: Distributed channel network + reservoir | L10: Flow through 1D/2D/3D network | M10: Chemical repair / deposition / replenishment | N10: Microcrack → component | O10: Minutes–days | P10: Multi-cycle; potentially continuous if externally replenished | Q10: Barrier; mechanics; function-specific | R10: Use a connected distribution network when damage is recurrent, internal, or requires more material than a local reservoir can hold. | S10: Repeated same-zone damage; large components; inaccessible internal cracks | T10: Network volume and complexity; network itself can fail | U10: Channel blockage/cut; insufficient pressure; no path to damage | V10: NR05, NR11, NR15 | W10: Cremaldi & Bhushan 2018; microvascular self-healing literature | X10: High
A11: NR07 | B11: Layer / renew / shed | C11: 0 Prevent + 5 Remodel | D11: Canonical: layering + replenishable coatings; extended: abscission | E11: Snake molting; tree bark; lotus wax; plant abscission | F11: Maintain a healthy exposed surface despite wear, fouling, or local damage. | G11: Grow/replenish new layer from within → protect next layer → optionally weaken boundary → shed damaged/old material. | H11: Wear; growth; programmed biochemical signal | I11: Fresh surface is exposed | J11: New layer / wax / secreted material | K11: Produced beneath or at surface | L11: Growth / secretion | M11: Replacement rather than patching | N11: Surface | O11: Periodic / continuous | P11: Continuous with resource supply | Q11: Surface protection / cleanliness | R11: When the outer layer is expendable, replace it instead of repeatedly repairing the same degraded material. | S11: High-cycle surface wear; coatings; self-cleaning; replaceable skins | T11: Consumes material and creates waste | U11: Replacement rate too slow; shedding damages substrate | V11: NR01, NR02, NR16 | W11: Cremaldi & Bhushan 2018 — layering, lotus, abscission | X11: High
A12: NR08 | B12: Dynamic rebond | C12: 4 Reconstruct | D12: Extended: reversible molecular network | E12: Protein networks; extracellular-matrix-like hydrogels; mussel-inspired coordination | F12: Restore continuity after bonds break while preserving repeated use. | G12: Damage breaks reversible bonds → chain/segment mobility enables recontact → bonds exchange/reform → network continuity returns. | H12: Contact; heat; water; pH; light; ions | I12: Broken network reconnects | J12: Intrinsic dynamic bonds | K12: Distributed throughout matrix/interface | L12: Molecular diffusion / exchange | M12: Dynamic covalent or supramolecular rebonding | N12: Molecular → interface | O12: Seconds–days | P12: Multi-cycle | Q12: Mechanical / electrical / adhesion depending network | R12: Build reversible bonds into the material so the same chemistry can repeatedly disconnect and reconnect. | S12: Small gaps; repeat damage; soft/semirigid polymers; hydrogels | T12: Strength–mobility trade-off | U12: Surfaces too far apart; low chain mobility; wrong activation conditions | V12: NR09, NR10, NR14, NR15 | W12: 2026 polymer/hydrogel reviews; enamel paper | X12: High
A13: NR09 | B13: Sacrificial dissipation + recovery | C13: 2 Stabilize + 4 Reconstruct | D13: Extended: sacrificial bond network | E13: Mussel byssus; bone; nacre; tough biological tissues | F13: Prevent catastrophic fracture by consuming energy in reversible secondary interactions. | G13: Load rises → weaker bonds/domain interfaces fail first → energy dissipates → primary backbone survives → weak interactions reform. | H13: Mechanical load/unload | I13: Crack driving force is reduced | J13: Weak reversible interactions | K13: Distributed hierarchy | L13: No long-range transport | M13: Reassociation of sacrificial network | N13: Molecular → mesoscale | O13: Immediate dissipation; recovery minutes–hours | P13: Multi-cycle if bonds recover | Q13: Toughness / fatigue resistance / mechanics | R13: Give the structure reversible 'fuses' that fail before the main load path and can reset afterward. | S13: Impact, fatigue, stretchable structures | T13: Hysteresis / residual strain / slower recovery | U13: Sacrificial network fails irreversibly or does not reform | V13: NR08, NR10, NR14 | W13: Mussel/byssus and tough hydrogel literature | X13: High
A14: NR10 | B14: Hierarchical crack control | C14: 0 Prevent + 2 Stabilize | D14: Extended: hierarchy / crack deflection | E14: Tooth enamel; nacre; bone; fibrous biological composites | F14: Combine stiffness/strength with crack resistance and local repairability. | G14: Aligned or layered hard phase carries load → interfaces redistribute stress/deflect crack → soft/dynamic phase dissipates and heals. | H14: Mechanical stress / crack initiation | I14: Propagation is slowed or redirected | J14: Hard reinforcement + compliant/dynamic interphase | K14: Distributed multiscale architecture | L14: Stress redistribution, not material transport | M14: Crack deflection + local repair | N14: Nano → component | O14: Immediate crack control + later healing | P14: Structural architecture persists | Q14: Strength, toughness, damage tolerance | R14: Separate load bearing and healing across scales so strong domains do not eliminate the mobility needed for repair. | S14: Load-bearing composites where conventional self-healing is too soft | T14: More reinforcement can suppress healing mobility | U14: Interface delamination or fiber failure cannot be restored by matrix healing alone | V14: NR08, NR09, NR16 | W14: 2026 enamel paper; 2026 composites review | X14: High
A15: NR11 | B15: Biomineralize / regrow missing material | C15: 4 Reconstruct | D15: Extended: biomineralization / deposition | E15: Bone/shell formation; bacteria, fungi, algae | F15: Replace lost volume with new solid material under ambient conditions. | G15: Damage exposes pathway + water/nutrients/ions → organism/metabolism or chemistry creates carbonate/mineral → nucleation → growth fills crack. | H15: Moisture; nutrients; ions; pH; metabolism | I15: New material nucleates in defect | J15: Mineral ions + metabolic products | K15: Ambient + embedded/external biological agent | L15: Diffusion / capillarity / growth | M15: Mineral precipitation / growth | N15: Surface → crack volume | O15: Days–weeks | P15: Multi-cycle while viable/resources accessible | Q15: Barrier; durability; sometimes mechanical recovery | R15: Use the damaged void as a reactor: bring precursors to it and grow a compatible solid phase in situ. | S15: Porous mineral materials; wet environments; inaccessible microcracks if agents are embedded | T15: Strong dependence on environmental window and access | U15: Only crack mouth heals; cells die; nutrients depleted; by-products undesirable | V15: NR03, NR05, NR06, NR16 | W15: van der Bergh thesis; B. pseudomycoides study; concrete reviews | X15: High for bacteria; Emerging for fungi/algae
... A20: NR16 | B20: Staged / temporal repair | C20: 2→5 sequence | D20: Extended: sequential response / homeostasis | E20: Hemostasis → inflammation/proliferation → remodeling; plant multistage defense | F20: Optimize for both survival-speed and restoration-quality without forcing one mechanism to do both. | G20: Phase 1 contain/seal → Phase 2 mobilize/reconstruct → Phase 3 remodel/verify → terminate response. | H20: Damage plus changing time/local chemistry | I20: Fast stabilization first | J20: Multiple resources separated by time or layer | K20: Local + networked | L20: Sequential release / recruitment | M20: Hybrid multi-mechanism | N20: Interface → component | O20: Seconds to long remodeling | P20: Repeatability depends on resources | Q20: Multiple functions in sequence | R20: Allocate different repair jobs to different timescales and coordinate handoff between them. | S20: Complex damage; corrosion protection; structural repair where speed and completeness conflict | T20: Coordination complexity | U20: Early seal prevents deeper agent penetration; late phase never activates | V20: NR02, NR03, NR06, NR08, NR11, NR15 | W20: Cremaldi & Bhushan 2018 homeostasis; 2026 time-gradient coating | X20: High

Sheet Biological Primitives
A1: Biological Repair Primitives — the smallest reusable mechanisms beneath the strategies
A2: The first eight primitives are the canonical mechanisms identified by Cremaldi & Bhushan (2018). The remaining primitives extend that framework using mechanisms repeatedly surfaced in the attached literature.
A4: Primitive ID | B4: Primitive | C4: Status | D4: Nature examples | E4: Core action | F4: Trigger / recognition | G4: Material / resource behavior | H4: Transport | I4: Spatial logic | J4: Temporal logic | K4: Repeatability | L4: Engineering abstraction | M4: Ontology strategies | N4: Key limitation | O4: Evidence
A5: P01 | B5: Reversible state change / muscle control | C5: Canonical 2018 | D5: Muscle; chameleon skin nanocrystals | E5: Switch physical state reversibly using controlled energy input | F5: Neural/chemical control; load/environment in analogues | G5: Actin–myosin or reversible structural spacing | H5: Local | I5: Distributed actuator | J5: Fast and reversible | K5: Lifetime-scale cycles | L5: Use reversible state transitions instead of permanent repair when the disturbance itself is transient. | M5: NR14 | N5: Requires energy/control and reversible kinetics | O5: Cremaldi & Bhushan 2018
A6: P02 | B6: Clotting / aggregation | C6: Canonical 2018 | D6: Vertebrate blood; invertebrate hemolymph | E6: Aggregate mobile material at breach to stop flow | F6: Damage + exposed wound chemistry | G6: Particles/cells/proteins aggregate | H6: Flow to breach | I6: Localized at leak | J6: Immediate | K6: Repeatable while circulating resources available | L6: Rapidly plug leakage first; restore structure later. | M6: NR03, NR16 | N6: May seal without restoring strength | O6: Cremaldi & Bhushan 2018
A7: P03 | B7: Cellular response / signaling | C7: Canonical 2018 | D7: Immune response; fibroblast recruitment; plant recognition | E7: Use local biochemical signals to trigger specialized actions | F7: Foreign material / damage-associated signal | G7: Specialized cells secrete, attack, remove, or build | H7: Signal/recruitment networks | I7: Damage-localized, system-coordinated | J7: Multi-stage | K7: Repeatable | L7: Separate detection, decision, and action; recruit the right function only where needed. | M7: NR15, NR16, NR12 | N7: Control errors can over/under-react | O7: Cremaldi & Bhushan 2018
A8: P04 | B8: Layering / periodic renewal | C8: Canonical 2018 | D8: Snake skin; epidermis | E8: Build a replacement layer beneath the old one and shed periodically | F8: Growth / lifecycle | G8: New layer grows from within | H8: Growth from substrate | I8: Surface-normal | J8: Periodic | K8: Continuous over life | L8: Renew an exposed surface rather than repairing every defect individually. | M8: NR07 | N8: Material/energy cost of renewal | O8: Cremaldi & Bhushan 2018
A9: P05 | B9: Protective surface | C9: Canonical 2018 | D9: Arthropod exoskeleton; tree bark | E9: Use a tough outer layer to absorb routine damage | F9: Passive exposure | G9: Hard/protective material | H9: None | I9: Outer boundary | J9: Continuous | K9: Persistent / renewed | L9: Move damage into a durable sacrificial boundary layer. | M9: NR01, NR10 | N9: Can hide sub-surface damage | O9: Cremaldi & Bhushan 2018
A10: P06 | B10: Vascular networks / capsules | C10: Canonical 2018 | D10: Weeping fig latex cells; vascular tissues | E10: Store/separate reactive resources and deliver them after damage | F10: Rupture / pressure / chemical trigger | G10: Stored fluid/resource is released or transported | H10: Capsule release or connected flow | I10: Distributed reservoirs/channels | J10: On-demand | K10: Capsule single-shot; networks multi-cycle | L10: Decouple storage from structural material and localize chemistry at the wound. | M10: NR05, NR06 | N10: Depletion / channel failure | O10: Cremaldi & Bhushan 2018
A11: P07 | B11: Exposure-induced closure / growth | C11: Canonical 2018 | D11: Plant wound closure/callus | E11: Exposure of internal tissue initiates swelling/division/hardening | F11: Exposure to air/environment after wound | G11: Cells expand, divide, mature, harden | H11: Local growth | I11: At exposed interface | J11: Delayed | K11: Repeatable with living tissue | L11: Use the newly exposed interface as the trigger and substrate for reconstruction. | M11: NR11, NR12 | N11: Requires viable growth system | O11: Cremaldi & Bhushan 2018
A12: P08 | B12: Replenishable functional coating | C12: Canonical 2018 | D12: Lotus epicuticular wax | E12: Continuously secrete a functional surface chemistry/topography | F12: Surface wear / ongoing metabolism | G12: Wax/chemistry replenishes functionality | H12: Secretion from epidermis | I12: Surface | J12: Continuous | K12: Continuous | L12: Make surface function renewable, not static. | M12: NR01, NR07 | N12: Replenishment must keep pace with wear | O12: Cremaldi & Bhushan 2018
A13: P09 | B13: Compartmentalization / boundary formation | C13: Ontology extension | D13: Trees — CODIT | E13: Seal damaged region away from healthy system | F13: Damage / infection signaling | G13: Physical + chemical wall formation | H13: Local | I13: Boundary around damage | J13: Rapid-to-persistent | K13: Repeatable in different zones | L13: Contain propagation when restoration is not worth the risk. | M13: NR02 | N13: Sacrifices local capacity | O13: Cremaldi & Bhushan 2018 tree section
A14: P10 | B14: Selective discard / abscission | C14: Ontology extension | D14: Leaves, fruit, damaged plant tissue | E14: Prepare safe boundary then deliberately weaken and detach expendable material | F14: Developmental/damage signal | G14: Enzymes degrade adhesion in separation zone | H14: Local biochemical delivery | I14: Predefined weak plane | J14: Staged | K14: Periodic | L14: Design a safe failure plane so damaged modules can detach without propagating failure. | M14: NR07, NR02, NR16 | N14: Requires redundancy/modularity | O14: Cremaldi & Bhushan 2018 plant abscission
A15: P11 | B15: Biomineralization / deposition | C15: Ontology extension | D15: Bone/shell; bacteria; fungi; algae | E15: Convert soluble precursors/metabolic products into solid repair mineral | F15: Moisture, ions, nutrients, pH, metabolism | G15: Nucleation + crystal growth | H15: Diffusion/capillarity/growth | I15: Damage void | J15: Days–weeks | K15: Finite to multi-cycle | L15: Grow compatible solid matter inside the defect. | M15: NR11 | N15: Access, by-products, viability, depth | O15: Concrete and biomineralization sources
... A20: P16 | B20: Remodeling / matrix turnover | C20: Ontology extension | D20: Bone; skin; tendon; regenerative tissues | E20: Remove damaged matrix and rebuild organized functional material over time | F20: Load/biochemical feedback | G20: Degradation + deposition + reorganization | H20: Cell/vascular transport | I20: Tissue volume | J20: Slow | K20: Continuous | L20: After closure, continue optimizing the repaired zone until system function—not geometry—is restored. | M20: NR12, NR16 | N20: Slow, resource-intensive, hard to engineer synthetically | O20: Regenerative biology + hydrogel literature

Sheet Biological Models
A1: Biological Models — natural systems as causal evidence anchors
A2: Models are stored separately from strategies: one organism may express several primitives, and the same strategy can be supported by multiple organisms. This prevents the engine from copying organism form without understanding mechanism.
A4: Model ID | B4: Domain | C4: Biological model | D4: Damage / challenge | E4: Natural response sequence | F4: Primitive IDs | G4: Strategy IDs | H4: Primary resources / energy | I4: Transport mode | J4: Spatial scale | K4: Temporal profile | L4: Repeatability | M4: Transferable rule | N4: Evidence / attached source
A5: M01 | B5: Animal tissue | C5: Soft-tissue wound healing | D5: Open wound; fluid loss; contamination; lost continuity | E5: Clot rapidly → immune cleanup/signaling → fibroblast/matrix deposition → remodeling | F5: P02,P03,P16 | G5: NR03,NR15,NR16,NR12 | H5: Circulating platelets/proteins; cells; metabolic energy | I5: Blood/vascular + cell migration | J5: Interface→tissue | K5: Immediate→weeks/months | L5: Repeated within biological limits | M5: Separate urgent stabilization from slower restoration and remodeling. | N5: 322753.pdf
A6: M02 | B6: Animal circulation | C6: Blood clotting / hemostasis | D6: Breach causes fluid loss | E6: Damage exposes wound → platelets/proteins aggregate → plug forms → homeostasis restored | F6: P02 | G6: NR03,NR16 | H6: Circulating clotting components | I6: Blood flow | J6: Localized breach | K6: Seconds–minutes | L6: Repeated while resources available | M6: Use flowing resources to aggregate specifically where containment is needed. | N6: 322753.pdf
A7: M03 | B7: Animal circulation | C7: Fibrinolysis | D7: Obstructive clot must be removed after it has served its purpose | E7: Enzymatic action dissolves clot → material becomes mobile → vessel function restored | F7: P15,P03 | G7: NR13,NR16 | H7: Enzymes + chemical energy | I7: Circulation/diffusion | J7: Vessel-local | K7: After stabilization | L7: Repeated | M7: Temporary repair material should be removable/recyclable when it becomes the next failure mode. | N7: Bio-inspired Self-Healing electrolytes for Li-S batteries 2017.pdf
A8: M04 | B8: Animal/plant | C8: Innate immune response | D8: Pathogen/damage crosses first barrier | E8: Recognize pattern → signal → recruit specialized response → remove threat / support repair | F8: P03 | G8: NR15,NR16 | H8: Cells, humoral factors, signaling molecules | I8: Circulation / local signaling | J8: Cell→organism | K8: Minutes→days | L8: Repeated | M8: Detect type of damage, not only magnitude; recruit a specialized response instead of a generic one. | N8: 322753.pdf
A9: M05 | B9: Animal | C9: Muscle reversible contraction | D9: Repeated deformation without permanent damage | E9: Chemical energy drives actin–myosin sliding → reversible contraction/relaxation | F9: P01 | G9: NR14 | H9: ATP / ions | I9: Local biochemical control | J9: Molecular→organ | K9: Milliseconds→seconds | L9: Very high cycle | M9: Design reversible active state changes with a reset path. | N9: 322753.pdf
A10: M06 | B10: Animal | C10: Chameleon skin nanocrystal spacing | D10: Change optical property reversibly | E10: Muscle/strain changes spacing/conformation of guanine nanocrystals → optical response reverses | F10: P01 | G10: NR14,NR15 | H10: Mechanical/chemical control | I10: Local | J10: Nano→surface | K10: Fast | L10: High cycle | M10: Change physical function through reversible geometry rather than material replacement. | N10: 322753.pdf
A11: M07 | B11: Animal tissue | C11: Multilayer skin / dermis | D11: Protect, sense, adhere, heal while layers have different roles | E11: Outer barrier limits exposure → dermis senses/responds → tissue repair restores continuity | F11: P05,P03,P16 | G11: NR01,NR15,NR16,NR12 | H11: Layered tissue + circulation | I11: Vascular/cellular | J11: Surface→tissue | K11: Immediate→long | L11: Repeated | M11: Separate conflicting functions spatially across layers and coordinate repair between them. | N11: 2026 skin/dermis papers in Papers (60)
A12: M08 | B12: Animal tissue | C12: Extracellular matrix / hydrated tissue network | D12: Maintain soft hydrated structure while constantly reorganizing | E12: Dynamic molecular interactions break/reform while cells remodel matrix | F12: P12,P16 | G12: NR08,NR12 | H12: Water, proteins/polymers, cells | I12: Diffusion/cellular | J12: Molecular→tissue | K12: Continuous | L12: Continuous | M12: A network can be stable at system scale while its local bonds are dynamic. | N12: Development of self-healing hydrogels with new functions using nanomaterials.pdf
A13: M09 | B13: Animal hard tissue | C13: Bone | D13: Carry load, dissipate cracks, remodel damage | E13: Hierarchy distributes stress → sacrificial interactions dissipate → cells resorb/deposit mineral → remodel to load | F13: P13,P14,P11,P16 | G13: NR09,NR10,NR11,NR12 | H13: Mineral ions, collagen, cells, metabolic energy | I13: Vascular/cellular | J13: Nano→organ | K13: Immediate→months | L13: Continuous | M13: Combine hierarchical toughening with long-term material replacement and load-guided remodeling. | N13: Bone-inspired papers in Papers (60)
A14: M10 | B14: Animal hard tissue | C14: Tooth enamel | D14: Extreme stiffness/strength with crack resistance | E14: Aligned mineral nanostructure redistributes load and limits crack propagation; engineered analogue adds dynamic interface | F14: P14,P12 | G14: NR10,NR08 | H14: Mineral hierarchy; engineered water/heat trigger in 2026 analogue | I14: Local molecular mobility | J14: Nano→component | K14: Immediate crack control; hours healing | L14: Repeatable in engineered analogue | M14: Use aligned hard reinforcement for load and a dynamic interphase for repair. | N14: s41467-026-72309-8.pdf
A15: M11 | B15: Marine animal | C15: Mussel byssus / plaque / cuticle | D15: Adhere and remain tough in wet, cyclic environments | E15: Catechol-rich chemistry forms strong wet interactions; metal coordination/sacrificial bonds dissipate and recover | F15: P12,P13 | G15: NR04,NR08,NR09 | H15: Catechol chemistry, metal ions | I15: Local diffusion/coordination | J15: Molecular→interface | K15: Fast→hours | L15: Multi-cycle for reversible bonds | M15: Pair wet-compatible adhesion with sacrificial reversible interactions. | N15: Multiple mussel papers in Papers (60)
... A34: M30 | B34: Microalgae | C34: Algae-based biomineralization | D34: Seal exposed concrete cracks sustainably | E34: Algae facilitate CaCO3 precipitation; photosynthesis requires light and environmental access | F34: P11 | G34: NR11 | H34: Light + CO2 + moisture + ions | I34: Surface diffusion/growth | J34: Exposed surface crack | K34: Days/weeks | L34: Potential repeated cycles with resources | M34: Match living agent ecology to damage accessibility; do not assume an exposed-surface model works deep inside opaque material. | N34: 126009167.pdf + van der Bergh thesis limitation

Sheet Challenge→Strategy
A1: Challenge → Strategy reasoning rules
A2: Use this sheet as the retrieval/selection layer: first classify the damage and operating conditions, then rank strategies. These are reasoning rules, not material prescriptions.
A4: Challenge pattern | B4: Critical qualifiers | C4: Prioritize | D4: Usually combine with | E4: De-prioritize / reject when | F4: Reasoning rule | G4: Biological model | H4: What to measure | I4: Evidence status | J4: Notes
A5: Urgent fluid leak / ingress through a new crack | B5: Need seconds–hours response; strength can recover later | C5: NR03 | D5: NR05/NR06 + NR16 | E5: Slow remodeling alone | F5: Stabilize homeostasis first: stop flow before optimizing structural restoration. | G5: Blood clotting / plant exudate | H5: Leakage/permeability immediately; strength separately | I5: High | J5: Do not label sealing as structural healing.
A6: Crack repeatedly reopens at same location | B6: Recurrence high; local payload may exhaust | C6: NR06 or NR08 | D6: NR15 + NR16 | E6: NR05 alone | F6: Favor replenishable transport or intrinsic reversible networks over one-shot reservoirs. | G6: Vascular transport / dynamic protein network | H6: Cycles to performance threshold | I6: High | J6: Record depletion mode.
A7: Deep internal crack with no maintenance access | B7: Repair location uncertain; resources must reach depth | C7: NR06 + NR11 | D7: NR15 | E7: Surface-only treatment | F7: Make access/transport a hard feasibility filter before chemistry selection. | G7: Vasculature + microbial mineralization | H7: Depth-resolved healing; transport reach | I7: High | J7: Surface closure can mask internal damage.
A8: Large gap; faces cannot physically re-contact | B8: Damage volume large | C8: NR06/NR11/NR12 | D8: NR03 | E8: NR08 alone | F8: If re-contact is impossible, supply or grow new material rather than rely only on rebonding. | G8: Vascular delivery / regeneration | H8: Volume filled + function recovery | I8: High | J8: Intrinsic systems often need alignment/re-contact.
A9: Very small recurrent microdamage in polymer | B9: Faces can re-contact; many cycles desired | C9: NR08 | D9: NR09/NR15 | E9: Finite capsule-only | F9: Use reversible molecular networks when damage is small and repeated. | G9: ECM/protein networks | H9: Mechanical/electrical recovery per cycle | I9: High | J9: Check activation temperature and mobility.
A10: High-load structural material must remain stiff | B10: Healing–strength trade-off is severe | C10: NR10 + NR09 | D10: NR08 | E10: Soft dynamic matrix alone | F10: Spatially separate load bearing from healing and use sacrificial interfaces. | G10: Enamel / nacre / bone | H10: Strength, toughness, healing %, residual stiffness | I10: High | J10: Too much rigid reinforcement can suppress chain mobility.
A11: Impact / high strain-rate hazard | B11: Need temporary stiffening + dissipation | C11: NR14 + NR09 | D11: NR10 | E11: Slow thermal healing as primary protection | F11: Match bond kinetics to loading rate so interactions 'lock' under fast loading but recover later. | G11: Bound-water network / muscle-like adaptability | H11: Rate-dependent modulus, hysteresis, recovery | I11: High | J11: Kinetic window is central.
A12: Corrosive environment after surface cracking | B12: Prevent ingress and restore barrier fast | C12: NR01 + NR03 | D12: NR16 + NR15 | E12: Mechanical recovery metric alone | F12: Treat barrier restoration as its own function; follow with deeper repair where needed. | G12: Skin/bark + clotting | H12: Permeability, corrosion indicators, coating integrity | I12: High | J12: Layered functions may reduce compromises.
A13: Concrete microcracks in moist/alkaline environment | B13: Water available; crack width and agent viability matter | C13: NR11 | D13: NR05/NR06/NR16 | E13: Biological route if organism cannot survive pH/temperature | F13: Use biomineralization when ecology and resource access match the substrate. | G13: Bacteria MICP | H13: Crack width/depth, permeability, CaCO3, strength | I13: High | J13: Organism/nutrient choice is a design variable.
A14: Concrete crack exposed at surface but not deep | B14: External treatment possible | C14: NR11 + external intervention mode | D14: NR03 | E14: Claiming full-depth healing from surface images | F14: Use surface-applied biorepair but quantify penetration separately. | G14: S. pasteurii / S. cohnii | H14: Depth profile + surface closure + permeability | I14: High | J14: External healing is not self-healing under strict RILEM definitions.
A15: Opaque internal concrete; proposed algae repair | B15: No light inside bulk | C15: Alternative NR11 agent (bacteria/fungi) | D15: NR06 | E15: Algae for deep internal cracks | F15: Reject biological models whose required environmental resource cannot reach the defect. | G15: Algae vs bacteria | H15: Light/resource availability + depth | I15: High | J15: Algae remain interesting for exposed/light-accessible surfaces.
... A22: Resource-constrained autonomous system | B22: No high heat/external service; long mission | C22: NR08/NR14 if ambient-compatible | D22: NR06 if refillable onboard | E22: Strategies needing high external energy | F22: Treat energy/resource budget as a selection constraint equal to healing efficiency. | G22: Homeostasis / passive dynamic networks | H22: Energy per repair, cycle count, residual function | I22: High | J22: Autonomy is not binary; specify energy and replenishment.

Sheet Evaluation Metrics
A1: Evaluation ontology — define what “healed” means before comparing solutions
A2: The attached concrete work makes this especially important: self-sealing, surface closure, strength recovery, permeability recovery, and deep crack repair are different outcomes and should never be collapsed into one generic healing percentage.
A4: Metric ID | B4: Metric / field | C4: Function class | D4: Definition / question | E4: Typical unit | F4: Required conditions to store | G4: Why needed | H4: Common misuse | I4: Preferred evidence | J4: Relevant strategies | K4: Example source | L4: Engine requirement
A5: E01 | B5: Surface crack closure | C5: Geometry / barrier | D5: How much of visible crack width/area disappears at the observed surface? | E5: % / µm | F5: Initial width; imaging method; location; time | G5: Useful but not sufficient | H5: Calling visible closure 'full healing' | I5: Image analysis + location | J5: NR03,NR11 | K5: B. pseudomycoides study | L5: Required for crack systems
A6: E02 | B6: Healing penetration depth | C6: Spatial completeness | D6: How far into the crack/volume does repair material extend? | E6: mm or depth-resolved % | F6: Crack geometry; scan method | G6: Prevents surface bias | H6: Assuming mouth closure equals internal repair | I6: X-ray CT / sectioning / 3D imaging | J6: NR05,NR06,NR11 | K6: B. pseudomycoides study | L6: Required when damage has depth
A7: E03 | B7: Permeability / watertightness recovery | C7: Barrier | D7: How much fluid transport is reduced/restored? | E7: coefficient / % recovery | F7: Pressure/head; fluid; crack width; time | G7: Direct durability function | H7: Using strength recovery as proxy for sealing | I7: Permeability test | J7: NR03,NR11 | K7: van der Bergh thesis | L7: Required for ingress-sensitive systems
A8: E04 | B8: Strength recovery | C8: Mechanical | D8: Recovery of peak load/strength after damage and repair | E8: MPa / % | F8: Loading mode; damage severity; cure/heal condition | G8: Separates structural healing from sealing | H8: Claiming healing from closure alone | I8: Mechanical test | J8: NR08,NR10,NR11 | K8: van der Bergh thesis | L8: Required for load-bearing systems
A9: E05 | B9: Stiffness recovery | C9: Mechanical | D9: Recovery of elastic modulus / stiffness | E9: GPa / % | F9: Test method; strain range | G9: Relevant to deflection and structural function | H9: Ignoring stiffness when strength recovers | I9: Mechanical test | J9: NR08,NR10 | K9: Polymer/composite reviews | L9: Conditional
A10: E06 | B10: Toughness / fracture energy recovery | C10: Mechanical | D10: Recovery of energy absorption/crack resistance | E10: MJ m⁻3 / KIC / % | F10: Crack geometry; loading rate | G10: Captures damage tolerance | H10: Using tensile strength alone | I10: Fracture/tensile integration | J10: NR09,NR10 | K10: Enamel / ionogel studies | L10: Conditional
A11: E07 | B11: Adhesion recovery | C11: Interface | D11: Recovery of interfacial bond or peel/shear performance | E11: MPa / N m⁻1 / % | F11: Wet/dry state; substrate; rate | G11: Needed for coatings/adhesives | H11: Visible closure as adhesion proof | I11: Peel/lap-shear/tack | J11: NR04 | K11: Mussel-inspired papers | L11: Required for interfaces
A12: E08 | B12: Electrical / signal recovery | C12: Functional | D12: Does conductivity, resistance response, or device signal return? | E12: S m⁻1 / Ω / % | F12: Bias; strain; temperature; signal protocol | G12: Measures actual device function | H12: Mechanical healing ≠ electrical healing | I12: Electrical test before/after | J12: NR15,NR08 | K12: Sensor/hydrogel sources | L12: Required for electronics
A13: E09 | B13: Actuation recovery | C13: Functional | D13: Does force/displacement/actuation performance return? | E13: % / force / strain | F13: Drive conditions | G13: Needed for artificial muscle/soft robotics | H13: Ignoring function beyond mechanics | I13: Actuation test | J13: NR14 | K13: Artificial muscle paper | L13: Conditional
A14: E10 | B14: Healing time / kinetics | C14: Temporal | D14: Time to reach defined recovery threshold | E14: s/min/h/d | F14: Target metric + threshold + environment | G14: Enables phase matching | H14: Reporting time without recovery threshold | I14: Time-resolved recovery | J14: All | K14: Wound/time-gradient analogies | L14: Required
A15: E11 | B15: Time-stage profile | C15: Temporal | D15: Which functions recover in which order? | E15: Sequence / timepoints | F15: Metrics at each phase | G15: Captures biological sequencing | H15: Single endpoint hides delays/trade-offs | I15: Time series | J15: NR16 | K15: Cremaldi & Bhushan; time-gradient coating | L15: Required for staged systems
... A24: E20 | B24: Evidence quality / peer-review status | C24: Provenance | D24: What type of source supports the claim? | E24: Primary/review/thesis/preprint/SI | F24: Publication status; DOI | G24: Weights ontology assertions | H24: Treating preprint/SI as equal to validated primary study | I24: Source classification | J24: All | K24: Attached source set | L24: Required

Sheet Attached Sources
A1: Attached-source review and ontology integration log
A2: All attached files are catalogued here. Evidence status is explicit: primary research, review, thesis, conference paper, supporting information, or non-peer-reviewed preprint. Only source-supported mechanisms were integrated; overlapping reviews are used mainly to strengthen vocabulary, constraints, and provenance.
A4: File | B4: Title / identification | C4: Year | D4: Source type | E4: Peer-review / status | F4: Main ontology contribution | G4: Strategies / primitives informed | H4: Key constraint or nuance integrated | I4: DOI / source URL | J4: Use in ontology | K4: Evidence weight | L4: Notes
A5: 2023vanderBerghphd.pdf | B5: Bio-inspired Bacteria-based Concrete for Durability Increase of Structures — John Milan van der Bergh, Liverpool John Moores University PhD thesis | C5: 2023 | D5: PhD thesis | E5: Examined thesis; cites and reports peer-reviewed studies | F5: Self-healing terminology; autogenic/autonomic/external healing; MICP pathways; external bacterial repair; nutrient microenvironment; capsules/vascular delivery; evaluation metrics | G5: NR05, NR06, NR11, NR16; P06, P11 | H5: Distinguish self-sealing from mechanical healing; external healing is a different intervention mode; nutrient medium, crack depth, field conditions and cost matter | I5: https://doi.org/10.1016/j.conbuildmat.2020.118557 | J5: Major ontology source | K5: High for synthesis; primary findings in thesis | L5: Includes associated peer-reviewed publications.
A6: 322753.pdf | B6: Bioinspired self-healing materials: lessons from nature — Cremaldi & Bhushan | C6: 2018 | D6: Peer-reviewed review | E6: Open-access review | F6: Canonical eight biological healing mechanisms; animal/plant comparisons; clotting, cellular response, layering, protective surfaces, vascular/capsule delivery, exposure, replenishable coatings; CODIT and abscission examples | G6: NR01–NR07, NR14–NR16; P01–P10 | H6: Provides biological primitives, not just material mechanisms; emphasizes immediate homeostasis before slower repair | I6: https://doi.org/10.3762/bjnano.9.85 | J6: Foundational ontology backbone | K6: Very high | L6: Primary biological taxonomy source for this workbook.
A7: 126009167.pdf | B7: Bio-inspired Self-Healing Concrete using Algae-Based Healing Agents for Crack Repair | C7: 2025 | D7: Conference proceedings / review-style paper | E7: Published proceedings | F7: Algae-facilitated CaCO3 biomineralization; renewable biological agent; repeated healing conditional on resources | G7: NR11; P11 | H7: Algae require light/CO2/moisture; deep opaque cracks therefore need explicit feasibility screening | I7: https://doi.org/10.2991/978-94-6463-662-8_78 | J7: Biological-agent option + resource constraint | K7: Medium | L7: Cross-checked against van der Bergh thesis limitation on internal light access.
A8: A_review_on_self-healing_concrete_A_biological_app.pdf | B8: A Review on Self-healing Concrete — A Biological Approach — Dilshad Kakasor Jaf | C8: 2023 | D8: Peer-reviewed review | E8: Published review | F8: Biological concrete healing; water-activated CaCO3 crack filling; bacterial concrete terminology and durability context | G8: NR03, NR11; P11 | H8: Water availability is an activation condition; sealing/permeability and structural performance are distinct | I8: https://doi.org/10.5937/ror2301001J | J8: Supporting concrete ontology vocabulary | K8: Medium–High | L8: Overlaps with stronger thesis/reviews; used as corroboration.
A9: Bio_inspired_self_healing_of_concrete_cr.pdf | B9: Bio-inspired self-healing of concrete cracks using new B. pseudomycoides species | C9: 2021 | D9: Primary research article | E9: Peer reviewed | F9: B. pseudomycoides HASS3 MICP crack repair; X-ray microtomography shows strong surface but weak deep healing | G9: NR11; P11 | H9: 0.4 mm crack mouth fully healed while deeper maximum healing ratio reported only ~14%; penetration depth must be measured | I9: Attached primary PDF | J9: Critical evidence for E02 penetration depth | K9: Very high | L9: Key example of why visible closure is not equivalent to full-volume repair.
A10: Bio-inspired Self-Healing electrolytes for Li-S batteries 2017.pdf | B10: Bio-inspired Self-Healing Electrolytes for Li-S Batteries — Choi & Wang preview/commentary on Zhang et al. | C10: 2017 | D10: Journal preview/commentary | E10: Published journal item | F10: Fibrinolysis-inspired self-healing electrolyte; solid polysulfides dissolve into mobile phase, redistribute and re-enter electrochemical cycle | G10: NR13; P15 | H10: Repair can mean remobilizing existing matter rather than adding new repair material | I10: https://doi.org/10.1016/j.chempr.2017.08.009 | J10: Created NR13 phase-transfer recycling strategy | K10: Medium–High | L10: Use as bioinspired conceptual anchor; underlying JACS study is the primary experiment.
A11: Bioinspired_Materials_for_Self-Cleaning_and_Self-H.pdf | B11: Bioinspired Materials for Self-Cleaning and Self-Healing — Youngblood & Sottos | C11: 2008 | D11: Peer-reviewed perspective/review | E11: Published MRS Bulletin article | F11: Autonomic site-specific healing; capsules, hollow fibers, microvascular networks; mechanochemical sensing; lotus-inspired renewable functional surfaces | G11: NR01, NR05, NR06, NR07, NR15 | H11: Future repair architectures should integrate sensing and circulatory delivery; scale matters | I11: Attached published PDF | J11: Foundational engineering bridge | K11: High | L11: Used to connect biological repair logic to materials architecture.
A12: Development of self-healing hydrogels with new functions using nanomaterials.pdf | B12: Development of self-healing hydrogels with new functions using nanomaterials — Lin, Li & Tao | C12: 2026 | D12: Peer-reviewed mini-review | E12: Published Nano Research review | F12: Dynamic bond vocabulary; ECM-like balance of destruction/reconstruction; multifunctional wound, sensing, magnetic, conductive and adhesive hydrogels | G12: NR08, NR12, NR15; P12, P16 | H12: Functional augmentation should be evaluated separately from mechanical healing; microenvironment responsiveness matters | I12: https://doi.org/10.26599/NR.2026.94908459 | J12: Updated dynamic-network and multifunction fields | K12: High | L12: 2026 source.
A13: epjconf_staaar2026_05005.pdf | B13: Advancements and Applications of Self-Healing Concrete for Sustainable Infrastructure | C13: 2026 | D13: Conference review | E13: Published proceedings | F13: Autogenous, biogenic and chemical encapsulation mechanisms; infrastructure applications; repeated/continuous vascular concepts; adoption barriers | G13: NR05, NR06, NR11 | H13: Crack-size range, moisture, scale-up, cost and standards constrain deployment | I13: https://doi.org/10.1051/epjconf/202635505005 | J13: Translation / maturity constraints | K13: Medium | L13: Review-level source; not used as sole support for mechanism.
A14: Ibrahim Galal Ibrahim Shaaban_PDF version.pdf | B14: Efficiency of Bacteria-Based Self-Healing Mechanism in Concrete — Shabban et al. | C14: n/a | D14: Research paper / proceedings | E14: Status not fully identified from extracted file | F14: Bacillus subtilis dose/concentration effects; partial crack sealing; mechanical-property improvement | G14: NR11; P11 | H14: Living-agent population and material age affect performance; source reports optimum among tested concentrations at 10^8 cells/mL | I14: Attached PDF | J14: Adds E16 viability/population dimension | K14: Medium | L14: Year/publication venue not asserted because not clear in extracted page.
A15: ICCESD-Concretesdoctorareviewonself-healingconcretetechnologies.pdf | B15: Concrete’s Doctor: A Review on Self-Healing Concrete Technologies | C15: 2026 | D15: Conference review | E15: Published conference proceedings | F15: MICP pathway; spore germination under water/nutrient access; fungi as emerging mineralization network; chemical/capsule comparisons | G15: NR05, NR11; P06, P11 | H15: pH/temperature/water control viability; fungi evidence remains limited; real-world standardization gaps | I15: Conference proceedings (ICCESD 2026) | J15: Adds biological-agent ecology and fungi node | K15: Medium | L15: Fungi classified as emerging evidence, not mature recommendation.
... A23: ssrn-6487565.pdf | B23: Self-Healing Ionogel for Strain and Self-Generated Voltage Sensor with Restored Performance | C23: n/a | D23: Preprint | E23: Not peer reviewed | F23: Reversible ionic + H-bond sacrificial interactions; reported 92.2% toughness healing after 12 h at 60°C; sensing function near restored | G23: NR08, NR09, NR15; P12, P13 | H23: Mechanical and sensing recovery can be tracked separately; evidence remains pre-peer-review | I23: https://ssrn.com/abstract=6487565 | J23: Adds multifunctional recovery example with low evidence weight | K23: Low–Medium | L23: Do not treat reported values as validated peer-reviewed evidence yet.

Sheet Reasoning Relations
A1: Knowledge-graph relations for machine reasoning
A2: Each row is a subject–relation–object assertion with a qualifier and evidence status. These triples are the bridge from spreadsheet taxonomy to a graph/RAG reasoning layer.
A4: Relation ID | B4: Subject | C4: Relation | D4: Object | E4: Qualifier / condition | F4: Reasoning implication | G4: Evidence basis | H4: Evidence type | I4: Confidence
A5: R001 | B5: M01 Soft-tissue wound | C5: USES_PRIMITIVE | D5: P02 Clotting | E5: First response | F5: Immediate stabilization precedes full reconstruction. | G5: 322753.pdf | H5: Source-derived | I5: High
A6: R002 | B6: M01 Soft-tissue wound | C6: USES_PRIMITIVE | D6: P03 Cellular response | E6: After hemostasis | F6: Damage triggers specialized recruitment/signaling. | G6: 322753.pdf | H6: Source-derived | I6: High
A7: R003 | B7: M01 Soft-tissue wound | C7: USES_PRIMITIVE | D7: P16 Remodeling | E7: Late phase | F7: Repair continues after closure until tissue organization/function improves. | G7: Biological healing framework | H7: Ontology synthesis | I7: High
A8: R004 | B8: NR03 Rapid plug/seal | C8: PRECEDES | D8: NR12 Living remodeling | E8: When fluid loss/ingress is urgent | F8: A fast containment layer can buy time for slower restoration. | G8: 322753.pdf | H8: Source-derived + abstraction | I8: High
A9: R005 | B9: NR16 Staged repair | C9: ORDERS | D9: NR03 → NR06/NR08/NR11 → NR12/NR15 | E9: Typical biological sequence | F9: Strategy selection should include temporal handoff. | G9: 322753.pdf | H9: Ontology synthesis | I9: High
A10: R006 | B10: M19 CODIT | C10: USES_PRIMITIVE | D10: P09 Compartmentalization | E10: When damage threatens spread | F10: Isolation can be a valid repair outcome even without restoring local material. | G10: 322753.pdf | H10: Source-derived | I10: High
A11: R007 | B11: NR02 Containment | C11: RESTORES_FUNCTION | D11: System-level continuity | E11: By sacrificing local zone | F11: Optimization target can be system survival rather than pristine local repair. | G11: 322753.pdf | H11: Ontology synthesis | I11: High
A12: R008 | B12: M20 Abscission | C12: PREPARES_BEFORE | D12: Selective discard | E12: Protective layer forms before separation | F12: Safe failure requires boundary preparation before release. | G12: 322753.pdf | H12: Source-derived | I12: High
A13: R009 | B13: M17 Lotus leaf | C13: COMBINES | D13: P08 Replenishable coating + hierarchical surface | E13: Surface function | F13: Repair/prevention can combine renewable chemistry and geometry. | G13: 322753.pdf | H13: Source-derived | I13: High
A14: R010 | B14: NR05 Reservoir release | C14: LIMITED_BY | D14: Finite payload | E14: At a given location | F14: One-shot delivery should not be chosen for high recurrence without redundancy/replenishment. | G14: 322753.pdf; 2026 composites review | H14: Source-derived | I14: High
A15: R011 | B15: NR06 Vascular transport | C15: CAN_REPLENISH | D15: Repair resources | E15: If connected to reservoir/external source | F15: Network architecture can support repeated local repair. | G15: 322753.pdf | H15: Source-derived | I15: High
... A54: R050 | B54: All strategies | C54: MUST_DECLARE | D54: Trigger + recovery conditions | E54: With quantitative performance | F54: A reported recovery is meaningful only under the stated activation environment. | G54: Enamel / polymer / concrete sources | H54: Ontology governance | I54: Very high

Sheet Ontology Bridge
A1: Repair sub-strategies → main ontology vocabulary
A2: Do NOT rename S1–S10. They are more precise than the main ontology and that precision is the asset. This sheet is the bridge that lets retrieval reach them.
A4: ID | B4: Repair sub-strategy (keep as is) | C4: ◄ Ontology function | D4: ◄ Ontology strategy | E4: ◄ Operating principle
A5: S1 | B5: Rapid seal / adhesion | C5: Protective envelope | D5: Selectively permeable boundary; surface sealing | E5: Locality
A6: S2 | B6: Reservoir release | C6: Energy harvesting & use | D6: Storage and timed release | E6: Gradient
A7: S3 | B7: Vascular transport | C7: Resistance reduction | D7: Flow optimization; branching network | E7: Gradient
A8: S4 | B8: Biomineralize / regrow | C8: Renewal | D8: Regrowth; material cycling | E8: Self-creation
A9: S5 | B9: Dynamic rebonding | C9: Renewal | D9: Sacrificial bonds; re-bonding | E9: Self-repair
A10: S6 | B10: Sacrificial-bond recovery | C10: Strength | D10: Energy absorption; sacrificial bonds | E10: Gradient
A11: S7 | B11: Hierarchical confinement / crack deflection | C11: Strength | D11: Layering; crack deflection; load distribution | E11: Multi-scale
A12: S8 | B12: Sense → signal → repair | C12: Communication & feedback | D12: Closed feedback loop; damage signalling | E12: Locality
A13: S9 | B13: Staged / temporal repair | C13: Renewal | D13: Cyclicity; staged sequence | E13: Spirality
A14: S10 | B14: Adaptive remodeling / living repair | C14: Adaptation | D14: Variation; behavioural flexibility | E14: Self-repair
A17: Why bridge instead of rename
A18: The precision is the asset | B18: 'Dynamic rebonding' says more than 'renewal'. Renaming S1–S10 to generic ontology terms would flatten a specialist vocabulary into a general one and lose the very thing that makes this set valuable.
A19: Retrieval needs both | B19: The engine reasons in ontology vocabulary. A founder's challenge maps to a function like Strength or Renewal. Without the bridge, none of these 60 papers can be reached from that starting point.
A20: This is the repository rule | B20: Every entry links back to the ontology, which is the index. The bridge is how that rule is satisfied without damaging the sub-ontology.
A22: Two things to confirm
A23: Exact term match | B23: The ontology names in columns C–E must match your main ontology spelling exactly, in whichever language the ontology is canonical. If the ontology is Hebrew, translate these three columns to the Hebrew terms — a near-match will not retrieve.
A24: One-to-many is expected | B24: Several sub-strategies map to the same function (S4, S5 and S9 all sit under Renewal). That is correct — it means the ontology function is the general case and the sub-strategy is the specific mechanism beneath it.

Sheet Maturity Guide
A1: Maturity — how to fill it
A2: Why it was added | B2: 'Engineering implementation' says what was built. It does not say whether that was one sample in a lab, a pilot line, or a running production process — nor what blocks scale-up. For a founder planning timelines and fundraising, that difference is worth months.
A4: The five levels
A5: Lab-scale | B5: Demonstrated in a paper, single samples, controlled conditions. Unknown whether it survives manufacture.
A6: Pilot / scaled demo | B6: Larger batches or a pilot line. Not commercial.
A7: In production | B7: Someone manufactures with it today. Always name WHICH industry — mature in food packaging can be lab-scale in medical devices.
A8: Commodity | B8: Several suppliers, standard equipment, known price.
A9: N/A — biological mechanism | B9: The row anchors a natural mechanism, not an engineered system. Maturity does not apply.
A11: Two mandatory companions
A12: Maturity evidence | B12: What the level rests on: a single paper, several groups, a patent, a reported pilot line, or a product on sale. 'One 2023 paper' and 'three companies manufacturing' are different confidence levels entirely.
A13: Scale-up blocker | B13: The specific barrier: yield, rate, uniformity, equipment cost, feedstock availability, or regulatory approval. One sentence. This is what turns maturity from information into action.
A15: Read this before trusting the column
A16: Most values are INFERRED, not verified | B16: Rows marked 'Lab-scale (assumed)' were inferred from the type of paper, not confirmed by research. They are shaded red and marked [VERIFY]. Do not let the engine present an inferred level as a checked one.
A17: Guessing here is expensive | B17: A founder plans timelines and fundraising on maturity. An unverified guess presented confidently is the failure mode most likely to lose a technical founder's trust. 'Searched, did not resolve' is a legitimate value and is in the dropdown.
A18: Discussion volume is not maturity | B18: A widely discussed technique sounds closer to production than it is.
